Workbook

Sheet Resumen Ejecutivo
A1: Análisis de mallas curriculares y aplicación de simuladores de negocios
A2: Universidad Libre – Facultad de Ingeniería · Ingeniería Industrial (SNIES 54334) e Ingeniería de Sistemas (SNIES 11584) · SimVenture · SimAgile · SimProject · catálogo CompanyGame · desarrollos propios
A4: 1. Alcance del análisis
A5: Se analizaron, asignatura por asignatura, las dos mallas curriculares entregadas por el cliente, para identificar dónde pueden integrarse SimVenture, SimAgile, SimProject y el catálogo CompanyGame, y dónde existe oportunidad de desarrollar simuladores propios.
A6: Fuente de las mallas: los dos PDF de la Facultad de Ingeniería de la Universidad Libre. Fuente del catálogo CompanyGame: el cuadro de portafolio entregado por el cliente (41 simuladores en 7 familias). No se incorporó ninguna asignatura ni ningún simulador que no aparezca en esos documentos.
A8: 2. Asignaturas analizadas
A9: Indicador | B9: Ing. Industrial | C9: Ing. de Sistemas | D9: Total
A10: Asignaturas en la malla | B10: =COUNTA('Ing. Industrial'!C5:C57) -> 53 | C10: =COUNTA('Ing. de Sistemas'!C5:C57) -> 53 | D10: =B10+C10 -> 106
A11: Créditos totales del programa | B11: =SUM('Ing. Industrial'!D5:D57) -> 144 | C11: =SUM('Ing. de Sistemas'!D5:D57) -> 144 | D11: =B11+C11 -> 288
A12: Asignaturas del componente Profesional | B12: =COUNTIF('Ing. Industrial'!E5:E57,"Profesional") -> 25 | C12: =COUNTIF('Ing. de Sistemas'!E5:E57,"Profesional") -> 27 | D12: =B12+C12 -> 52
A13: Espacios electivos y optativos sin contenido definido | B13: =COUNTIF('Ing. Industrial'!J5:J57,"No evaluable") -> 6 | C13: =COUNTIF('Ing. de Sistemas'!J5:J57,"No evaluable") -> 6 | D13: =B13+C13 -> 12
A15: 3. Oportunidades por simulador (número de asignaturas)
A16: Simulador | B16: Alta – Industrial | C16: Alta – Sistemas | D16: Media – Industrial | E16: Media – Sistemas | F16: Total Alta + Media
A17: SimVenture | B17: =COUNTIF('Ing. Industrial'!J5:J57,"Alta") -> 1 | C17: =COUNTIF('Ing. de Sistemas'!J5:J57,"Alta") -> 1 | D17: =COUNTIF('Ing. Industrial'!J5:J57,"Media") -> 0 | E17: =COUNTIF('Ing. de Sistemas'!J5:J57,"Media") -> 0 | F17: =SUM(B17:E17) -> 2
A18: SimAgile | B18: =COUNTIF('Ing. Industrial'!K5:K57,"Alta") -> 1 | C18: =COUNTIF('Ing. de Sistemas'!K5:K57,"Alta") -> 1 | D18: =COUNTIF('Ing. Industrial'!K5:K57,"Media") -> 0 | E18: =COUNTIF('Ing. de Sistemas'!K5:K57,"Media") -> 0 | F18: =SUM(B18:E18) -> 2
A19: SimProject | B19: =COUNTIF('Ing. Industrial'!L5:L57,"Alta") -> 1 | C19: =COUNTIF('Ing. de Sistemas'!L5:L57,"Alta") -> 2 | D19: =COUNTIF('Ing. Industrial'!L5:L57,"Media") -> 0 | E19: =COUNTIF('Ing. de Sistemas'!L5:L57,"Media") -> 0 | F19: =SUM(B19:E19) -> 3
A20: Desarrollo propio (oportunidad) | B20: =COUNTIF('Ing. Industrial'!P5:P57,"Alta") -> 13 | C20: =COUNTIF('Ing. de Sistemas'!P5:P57,"Alta") -> 6 | D20: =COUNTIF('Ing. Industrial'!P5:P57,"Media") -> 18 | E20: =COUNTIF('Ing. de Sistemas'!P5:P57,"Media") -> 16 | F20: =SUM(B20:E20) -> 53
A22: Catálogo CompanyGame — grado de ajuste (columna única, mismo formato del mapeo de la UAO)
A23: Grado de ajuste | B23: Ing. Industrial | C23: Ing. de Sistemas | D23: Total
A24: Encaje perfecto | B24: =COUNTIF('Ing. Industrial'!O5:O57,"Encaje perfecto") -> 7 | C24: =COUNTIF('Ing. de Sistemas'!O5:O57,"Encaje perfecto") -> 4 | D24: =B24+C24 -> 11
A25: Encaje parcial | B25: =COUNTIF('Ing. Industrial'!O5:O57,"Encaje parcial") -> 3 | C25: =COUNTIF('Ing. de Sistemas'!O5:O57,"Encaje parcial") -> 5 | D25: =B25+C25 -> 8
A26: No encaja | B26: =COUNTIF('Ing. Industrial'!O5:O57,"No encaja") -> 37 | C26: =COUNTIF('Ing. de Sistemas'!O5:O57,"No encaja") -> 38 | D26: =B26+C26 -> 75
A27: Por definir | B27: =COUNTIF('Ing. Industrial'!O5:O57,"Por definir") -> 6 | C27: =COUNTIF('Ing. de Sistemas'!O5:O57,"Por definir") -> 6 | D27: =B27+C27 -> 12
A28: Los conteos se calculan con fórmulas sobre las hojas 'Ing. Industrial' e 'Ing. de Sistemas': si se ajusta una calificación, este resumen se actualiza solo.
A30: 4. Principales hallazgos
A31: • Ingeniería Industrial es el programa natural de SimVenture y de las familias CompanyGame de Negocios y estrategia y de Finanzas: la línea de gestión empresarial atraviesa los semestres II a VII (Contabilidad y Presupuesto, Gestión Organizacional, Gerencia Estratégica, Costos de Operación, Ingeniería Económica, Finanzas y Mercadeo).
A32: • Ingeniería de Sistemas es el programa natural de SimAgile y SimProject: la línea de Ingeniería de Software recorre los semestres III, IV y V y culmina en Gestión de Proyectos de Ingeniería (VII), la asignatura de encaje más directo de todo el análisis.
A33: • Hallazgo del catálogo CompanyGame: CÁTEDRA DE SOSTENIBILIDAD es obligatoria en los dos programas, hoy no tiene ninguna herramienta práctica asociada y la familia ESG Management (ESGProject, ESGManagement, GlobalManagement) cubre su objeto completo. Es la mejor relación esfuerzo-resultado de todo el análisis: una sola conversación con doble resultado.
A34: • Segundo hallazgo del catálogo: ninguna de las dos mallas tiene asignatura de emprendimiento o creación de empresa. La familia Emprendimiento de CompanyGame sólo tiene entrada indirecta por Formulación y Evaluación de Proyectos, o directa si se diseña una electiva.
A35: • La familia HORECA no tiene ninguna asignatura destino en estas dos mallas. Se registra en Baja de forma explícita; su mercado está en otros programas de la universidad, no en la Facultad de Ingeniería.
A36: • Los simuladores CompanyGame de nivel 1-2 (T-Shirt, Sunny Day, MarketGame, ContaTrainer) abren una entrada temprana que SimVenture, SimAgile y SimProject no cubren: Introducción a la Ingeniería (I, ambos programas) y Contabilidad y Presupuesto (II, Industrial).
A37: • Tres asignaturas admiten dos simuladores a la vez y permiten proponer paquetes: Formulación y Evaluación de Proyectos (en ambos programas), Ingeniería del Software III y Diseño de Productos y Servicios.
A38: • La ausencia más grande del portafolio está en la línea de producción y operaciones de Ingeniería Industrial: ocho asignaturas del componente profesional sin simulador aplicable, ni propio ni del catálogo CompanyGame. Es el mayor espacio de desarrollo propio identificado.
A39: • Los 6 espacios electivos y optativos de cada programa (12 en total) no tienen contenido definido en la malla y constituyen la vía de inserción más rápida: permiten proponer un curso basado en simulador sin pasar por un rediseño curricular.
A40: • El componente de ciencias básicas y la formación humanística no ofrecen oportunidades reales. Se calificaron como Baja de forma explícita para evitar recomendaciones que no resistirían una revisión académica.
A42: 5. Top 15 oportunidades con mayor potencial de implementación
A43: # | B43: Programa | C43: Sem. | D43: Asignatura | E43: Simulador recomendado | F43: Prioridad | G43: Facilidad de justificación
A44: 1 | B44: Ing. de Sistemas | C44: Semestre 7 | D44: GESTIÓN DE PROYECTOS DE INGENIERÍA | E44: SimProject | F44: Alta | G44: Alta
A45: 2 | B45: Ing. Industrial | C45: Semestre 4 | D45: GERENCIA ESTRATÉGICA | E45: SimVenture | F45: Alta | G45: Alta
A46: 3 | B46: Ing. Industrial | C46: Semestre 7 | D46: FORMULACIÓN Y EVALUACIÓN DE PROYECTOS | E46: SimVenture + SimProject | F46: Alta | G46: Alta
A47: 4 | B47: Ing. de Sistemas | C47: Semestre 5 | D47: INGENIERÍA DEL SOFTWARE III | E47: SimAgile + SimProject | F47: Alta | G47: Alta
A48: 5 | B48: Ing. Industrial | C48: Semestre 6 | D48: FINANZAS | E48: SimVenture | F48: Alta | G48: Alta
A49: 6 | B49: Ambos programas | C49: V (Ind.) / IV (Sist.) | D49: CÁTEDRA DE SOSTENIBILIDAD | E49: ESGManagement / ESGProject (CompanyGame) | F49: Alta | G49: Alta
A50: 7 | B50: Ing. de Sistemas | C50: Semestre 6 | D50: FORMULACIÓN Y EVALUACIÓN DE PROYECTOS | E50: SimProject + SimVenture | F50: Alta | G50: Alta
A51: 8 | B51: Ing. Industrial | C51: Semestre 6 | D51: MERCADEO | E51: SimVenture | F51: Alta | G51: Alta
A52: 9 | B52: Ing. de Sistemas | C52: Semestre 4 | D52: INGENIERÍA DE SOFTWARE II | E52: SimAgile | F52: Alta | G52: Alta
A53: 10 | B53: Ing. Industrial | C53: Semestre 5 | D53: DISEÑO DE PRODUCTOS Y SERVICIOS | E53: SimAgile + SimVenture | F53: Alta | G53: Alta
A54: 11 | B54: Ing. de Sistemas | C54: Semestre 8 | D54: ARQUITECTURA EMPRESARIAL | E54: SimAgile + SimVenture | F54: Alta | G54: Media
A55: 12 | B55: Ing. Industrial | C55: Semestre 6 | D55: GESTIÓN DE TECNOLOGÍA | E55: SimAgile | F55: Alta | G55: Alta
... A58: 15 | B58: Ing. de Sistemas | C58: Semestre 3 | D58: INGENIERÍA DE SOFTWARE I | E58: SimAgile | F58: Alta | G58: Alta
A59: El detalle de cada oportunidad, con la alternativa CompanyGame y el argumento de venta, está en la hoja 'Priorización' (23 oportunidades en total).
A61: 6. Principales oportunidades de desarrollo propio
A62: Código | B62: Simulador propuesto | C62: Programas | D62: Transversalidad | E62: Prioridad
A63: DP-01 | B63: Simulador de Planeación y Control de Operaciones | C63: Ing. Industrial | D63: Alta - 6 asignaturas de un programa | E63: Prioridad 1
A64: DP-02 | B64: Simulador de Transformación Digital y Arquitectura Empresarial | C64: Ing. de Sistemas + Ing. Industrial | D64: Alta en asignaturas (6 en los dos programas), pero ya cubierta parcialmente por el catálogo | E64: Prioridad 3 (cubierto parcialmente por CompanyGame)
A65: DP-03 | B65: Simulador de Implementación y Auditoría de Sistemas Integrados de Gestión | C65: Ing. Industrial + Ing. de Sistemas | D65: Alta - 5 asignaturas en los dos programas | E65: Prioridad 1
A66: DP-04 | B66: Simulador de Cadena de Suministro | C66: Ing. Industrial | D66: Alta - 4 asignaturas de un programa | E66: Prioridad 2
A67: DP-05 | B67: Simulador de Gestión de Incidentes de Seguridad de la Información | C67: Ing. de Sistemas | D67: Media - 3 asignaturas de un programa | E67: Prioridad 2
A68: DP-06 | B68: Simulador de Control Estadístico de Procesos y Calidad | C68: Ing. Industrial | D68: Media - 3 asignaturas de un programa | E68: Prioridad 2
A69: DP-07 | B69: Simulador de Dilemas Éticos y Sostenibilidad en la Decisión Profesional | C69: Ing. Industrial + Ing. de Sistemas | D69: Media - queda acotado a ÉTICA (ambos programas) e INTELIGENCIA ARTIFICIAL | E69: Prioridad 3
A70: DP-08 | B70: Simulador de Seguridad y Salud en el Trabajo (SG-SST) | C70: Ing. Industrial | D70: Baja - 2 asignaturas de un programa | E70: Prioridad 3
A71: DP-09 | B71: Simulador de Diseño de Instalaciones y Procesos Industriales | C71: Ing. Industrial | D71: Media - 3 asignaturas de un programa | E71: Prioridad 3
A72: DP-10 | B72: Línea de laboratorios virtuales (producto distinto a simuladores de gestión) | C72: Ing. Industrial + Ing. de Sistemas | D72: Alta en número de asignaturas (5), pero corresponde a otra línea de producto | E72: Fuera del alcance de simuladores de gestión
A75: 7. Criterios de calificación de compatibilidad
A76: ALTA | B76: El objeto central de aprendizaje de la asignatura coincide con el dominio de decisión que modela el simulador. El simulador puede ser eje del curso o de una unidad completa y sus decisiones corresponden directamente a las competencias declaradas.
A77: MEDIA | B77: El dominio del simulador cubre una parte de la asignatura (una unidad, un eje transversal o el contexto). Aporta como actividad complementaria o de integración, pero no cubre el núcleo del curso.
A78: BAJA | B78: La asignatura pertenece a ciencias básicas, formación humanística o a un dominio técnico específico sin decisiones de gestión, proyecto o negocio. El simulador no aporta a sus resultados de aprendizaje.
A79: NO EVALUABLE | B79: Espacios electivos y optativos cuyo contenido no está definido en la malla curricular. No es posible evaluar compatibilidad; se tratan como espacios de inserción curricular.
A80: DESARROLLO PROPIO - ALTA | B80: Existe un dominio de decisión claro y enseñable que ningún simulador del portafolio actual cubre, y la temática es transversal a dos o más asignaturas o programas.
A81: DESARROLLO PROPIO - MEDIA | B81: Existe un dominio simulable pero limitado a una sola asignatura, o bien pertenece a una línea de producto distinta (por ejemplo laboratorios virtuales).
A83: 8. Notas sobre la fuente y sus límites
A84: • Fuente del catálogo CompanyGame: el cuadro de portafolio entregado por el cliente, con 41 simuladores organizados en 7 familias y 4 rangos de nivel. Los nombres de los simuladores se transcriben literalmente de esa imagen; en dos casos (Acelera y Organization & People Management) la ubicación en el cuadro queda entre dos columnas de nivel y así se registra.
A85: • SimVenture, SimAgile y SimProject se analizan en columnas propias por tratarse de productos distintos del catálogo CompanyGame mostrado.
A86: • Fuente de las mallas: los dos PDF de malla curricular entregados por el cliente (Ingeniería Industrial SNIES 54334 e Ingeniería de Sistemas SNIES 11584, Facultad de Ingeniería, Universidad Libre).
A87: • Información explícita tomada de la fuente: nombre de la asignatura, semestre, número de créditos y componente de formación (identificado por el código de color de la malla: Básico, Electiva, Humanístico, Optativo, Profesional).
A88: • Información inferida por el analista: área temática, competencias, temáticas principales, relación con la gestión y todos los niveles de compatibilidad. Las mallas no incluyen contenidos programáticos ni resultados de aprendizaje.
A89: • Recomendación: validar las inferencias con los microcurrículos o syllabus de cada asignatura antes de la reunión comercial. Los syllabus no fueron suministrados.
A90: • Las asignaturas ELECTIVA I, II, III y OPTATIVA I, II, III no tienen contenido definido en la malla; se marcan como 'No evaluable' y se tratan como espacios de inserción curricular.
A91: • Observación sobre la fuente: en la malla de Ingeniería Industrial, el Semestre V aparece con un total de 19 créditos, pero la suma de las asignaturas listadas es 18 y el total del programa (144) sólo cuadra con 18. Conviene verificar este punto con el programa.
A92: • Ambos programas suman 144 créditos y 53 asignaturas (incluidos los espacios electivos y optativos).

Sheet Ing. Industrial
A1: Matriz de relacionamiento – Ingeniería Industrial
A2: Universidad Libre – Facultad de Ingeniería · SNIES 54334 · 53 asignaturas · 144 créditos
A4: Programa | B4: Semestre | C4: Asignatura | D4: Créditos | E4: Componente de formación | F4: Área temática | G4: Competencias principales | H4: Temáticas principales | I4: Relación con gestión / negocio | J4: SimVenture | K4: SimAgile | L4: SimProject | M4: Simulador CompanyGame que encaja | N4: Nivel CG | O4: Grado de ajuste | P4: Desarrollo propio | Q4: Tipo de simulador que se requeriría | R4: Simulador recomendado | S4: Justificación de la recomendación | T4: Tipo de uso sugerido | U4: Prioridad comercial | V4: Origen de competencias y temáticas
A5: Ingeniería Industrial | B5: Semestre 1 | C5: INTRODUCCIÓN A LA INGENIERÍA | D5: 2 | E5: Básico | F5: Fundamentación profesional | G5: Comprensión del campo de acción del ingeniero industrial; pensamiento sistémico inicial; trabajo en equipo | H5: Perfil y campos de la ingeniería industrial; sistemas productivos; rol profesional | I5: Media - contextualiza la empresa como objeto de la profesión | J5: Baja | K5: Baja | L5: Baja | M5: — | N5: — | O5: No encaja | P5: Baja | Q5: Cubierto parcialmente por el catálogo; el resto del curso se apoya en SimVenture, SimAgile o SimProject según el caso | R5: T-Shirt / Sunny Day (CompanyGame, nivel introductorio) | S5: El curso es de contextualización profesional, no de decisión empresarial. Un módulo introductorio corto de SimVenture puede usarse como actividad motivadora, pero no hay contenido que el simulador cubra. El catálogo CompanyGame sí ofrece una opción viable aquí: un simulador de nivel 1-2 como T-Shirt funciona como primera experiencia de decisión empresarial en primer semestre, con alto volumen de estudiantes y bajo esfuerzo docente. | T5: Exploratorio | U5: Media | V5: Inferencia académica
A6: Ingeniería Industrial | B6: Semestre 1 | C6: EXPRESIÓN GRÁFICA PARA INGENIERÍA | D6: 3 | E6: Básico | F6: Ciencias básicas de ingeniería | G6: Representación gráfica, normalización técnica, manejo de CAD | H6: Dibujo técnico, acotado, vistas, modelado CAD | I6: Nula - competencia técnica instrumental | J6: Baja | K6: Baja | L6: Baja | M6: — | N6: — | O6: No encaja | P6: Baja | Q6: No requiere simulador — asignatura sin decisiones de gestión, proyecto o negocio | R6: Ninguno | S6: No hay decisiones de gestión, proyecto ni negocio. Forzar un simulador aquí restaría credibilidad a la propuesta. | T6: No aplica | U6: Baja | V6: Inferencia académica
A7: Ingeniería Industrial | B7: Semestre 1 | C7: CÁLCULO DIFERENCIAL | D7: 3 | E7: Básico | F7: Ciencias básicas | G7: Razonamiento matemático, modelado de variación | H7: Límites, derivadas, optimización de funciones | I7: Nula | J7: Baja | K7: Baja | L7: Baja | M7: — | N7: — | O7: No encaja | P7: Baja | Q7: No requiere simulador — asignatura sin decisiones de gestión, proyecto o negocio | R7: Ninguno | S7: Asignatura de ciencias básicas sin componente de decisión empresarial. | T7: No aplica | U7: Baja | V7: Inferencia académica
A8: Ingeniería Industrial | B8: Semestre 1 | C8: QUÍMICA GENERAL Y LABORATORIO | D8: 3 | E8: Básico | F8: Ciencias básicas | G8: Fundamentos químicos aplicados a materiales y procesos; trabajo experimental | H8: Estequiometría, enlaces, reacciones, prácticas de laboratorio | I8: Nula para simuladores de gestión | J8: Baja | K8: Baja | L8: Baja | M8: — | N8: — | O8: No encaja | P8: Media | Q8: Laboratorio virtual de química (línea de producto distinta a los simuladores de gestión) | R8: Desarrollo propio (laboratorio virtual) | S8: No aplica a simuladores de negocio. Sí existe oportunidad para laboratorio virtual de química, que es una línea de producto distinta a los simuladores de gestión. | T8: No aplica | U8: Baja | V8: Inferencia académica
A9: Ingeniería Industrial | B9: Semestre 1 | C9: LÓGICA Y ALGORITMOS | D9: 3 | E9: Básico | F9: Ciencias básicas de ingeniería | G9: Pensamiento algorítmico, resolución estructurada de problemas | H9: Lógica proposicional, diagramas de flujo, pseudocódigo | I9: Nula | J9: Baja | K9: Baja | L9: Baja | M9: — | N9: — | O9: No encaja | P9: Baja | Q9: No requiere simulador — asignatura sin decisiones de gestión, proyecto o negocio | R9: Ninguno | S9: Competencia técnica sin decisiones de gestión de negocio, proyecto o equipo. | T9: No aplica | U9: Baja | V9: Inferencia académica
A10: Ingeniería Industrial | B10: Semestre 1 | C10: COMPETENCIAS DE APRENDIZAJE Y COMUNICACIÓN | D10: 3 | E10: Humanístico | F10: Formación humanística | G10: Comunicación oral y escrita, lectura crítica, trabajo colaborativo | H10: Competencias comunicativas, argumentación, trabajo en equipo | I10: Baja - toca trabajo en equipo pero no gestión | J10: Baja | K10: Baja | L10: Baja | M10: — | N10: — | O10: No encaja | P10: Baja | Q10: No requiere simulador — asignatura sin decisiones de gestión, proyecto o negocio | R10: Ninguno | S10: Aunque desarrolla trabajo en equipo, no hay contenido de gestión que justifique la inversión en un simulador. | T10: No aplica | U10: Baja | V10: Inferencia académica
A11: Ingeniería Industrial | B11: Semestre 1 | C11: CÁTEDRA UNILIBRISTA | D11: 1 | E11: Humanístico | F11: Formación institucional | G11: Identidad institucional y valores unilibristas | H11: Historia, principios y proyecto educativo institucional | I11: Nula | J11: Baja | K11: Baja | L11: Baja | M11: — | N11: — | O11: No encaja | P11: Baja | Q11: No requiere simulador — asignatura sin decisiones de gestión, proyecto o negocio | R11: Ninguno | S11: Cátedra institucional sin contenidos de gestión. | T11: No aplica | U11: Baja | V11: Inferencia académica
A12: Ingeniería Industrial | B12: Semestre 2 | C12: CÁLCULO INTEGRAL | D12: 3 | E12: Básico | F12: Ciencias básicas | G12: Razonamiento matemático, integración y acumulación | H12: Integrales, aplicaciones, series | I12: Nula | J12: Baja | K12: Baja | L12: Baja | M12: — | N12: — | O12: No encaja | P12: Baja | Q12: No requiere simulador — asignatura sin decisiones de gestión, proyecto o negocio | R12: Ninguno | S12: Ciencias básicas sin decisiones empresariales. | T12: No aplica | U12: Baja | V12: Inferencia académica
A13: Ingeniería Industrial | B13: Semestre 2 | C13: FÍSICA MECÁNICA Y LABORATORIO | D13: 3 | E13: Básico | F13: Ciencias básicas | G13: Modelado físico de sistemas mecánicos; experimentación | H13: Cinemática, dinámica, energía, laboratorio | I13: Nula para simuladores de gestión | J13: Baja | K13: Baja | L13: Baja | M13: — | N13: — | O13: No encaja | P13: Media | Q13: Laboratorio virtual de física | R13: Desarrollo propio (laboratorio virtual) | S13: Sin relación con simuladores de negocio; oportunidad únicamente en la línea de laboratorios virtuales. | T13: No aplica | U13: Baja | V13: Inferencia académica
A14: Ingeniería Industrial | B14: Semestre 2 | C14: ALGEBRA LINEAL | D14: 3 | E14: Básico | F14: Ciencias básicas | G14: Modelado matricial, solución de sistemas | H14: Matrices, vectores, espacios, transformaciones | I14: Nula | J14: Baja | K14: Baja | L14: Baja | M14: — | N14: — | O14: No encaja | P14: Baja | Q14: No requiere simulador — asignatura sin decisiones de gestión, proyecto o negocio | R14: Ninguno | S14: Ciencias básicas sin decisiones empresariales. | T14: No aplica | U14: Baja | V14: Inferencia académica
A15: Ingeniería Industrial | B15: Semestre 2 | C15: CIENCIA DE LOS MATERIALES EN LA INDUSTRIA | D15: 2 | E15: Básico | F15: Ciencias básicas de ingeniería | G15: Selección y caracterización de materiales industriales | H15: Estructura, propiedades, ensayos, selección de materiales | I15: Baja - la selección de materiales tiene impacto en costos | J15: Baja | K15: Baja | L15: Baja | M15: — | N15: — | O15: No encaja | P15: Media | Q15: Simulador de selección de materiales con trade-off costo–desempeño | R15: Desarrollo propio (selección de materiales / laboratorio virtual) | S15: El componente de decisión (costo vs. desempeño del material) existe pero es muy específico; ningún simulador del portafolio lo cubre. | T15: No aplica | U15: Baja | V15: Inferencia académica
A16: Ingeniería Industrial | B16: Semestre 2 | C16: LENGUAJE DE PROGRAMACIÓN | D16: 3 | E16: Básico | F16: Ciencias básicas de ingeniería | G16: Programación estructurada aplicada a problemas de ingeniería | H16: Sintaxis, estructuras de control, funciones, datos | I16: Nula | J16: Baja | K16: Baja | L16: Baja | M16: — | N16: — | O16: No encaja | P16: Baja | Q16: No requiere simulador — asignatura sin decisiones de gestión, proyecto o negocio | R16: Ninguno | S16: Competencia técnica de programación; sin decisiones de gestión. | T16: No aplica | U16: Baja | V16: Inferencia académica
... A21: Ingeniería Industrial | B21: Semestre 3 | C21: PROBABILIDAD Y ESTADÍSTICA DESCRIPTIVA | D21: 3 | E21: Básico | F21: Métodos cuantitativos | G21: Análisis de datos, caracterización de variables, inferencia inicial | H21: Distribuciones, medidas descriptivas, probabilidad | I21: Media - base para decisiones bajo incertidumbre | J21: Baja | K21: Baja | L21: Baja | M21: — | N21: — | O21: No encaja | P21: Media | Q21: Simulador de decisiones con datos incompletos y bajo incertidumbre | R21: Desarrollo propio (decisiones bajo incertidumbre) | S21: El curso enseña la herramienta, no la decisión. Un simulador propio que obligue a decidir con datos incompletos sería pertinente, pero ninguno del portafolio actual encaja. | T21: Exploratorio | U21: Baja | V21: Inferencia académica
A22: Ingeniería Industrial | B22: Semestre 3 | C22: DISEÑO EN INGENIERÍA | D22: 2 | E22: Básico | F22: Diseño y desarrollo de producto | G22: Proceso de diseño, identificación de necesidades, prototipado, trabajo en equipo multidisciplinar | H22: Metodología de diseño, requisitos, iteración, prototipos | I22: Alta - desarrollo de producto e innovación | J22: Baja | K22: Alta | L22: Baja | N22: — | O22: No encaja | P22: Media | Q22: Cubierto parcialmente por el catálogo; el resto del curso se apoya en SimVenture, SimAgile o SimProject según el caso | R22: SimAgile | S22: El diseño en ingeniería es iterativo y por equipos, que es exactamente la dinámica de SimAgile (ciclos, backlog, entrega incremental). SimVenture aportaría la validación comercial del diseño. | T22: Complementario | U22: Media | V22: Inferencia académica
A23: Ingeniería Industrial | B23: Semestre 3 | C23: FUNDAMENTO DE ECONOMÍA | D23: 3 | E23: Profesional | F23: Economía y entorno | G23: Comprensión del funcionamiento de mercados y del entorno económico de la empresa | H23: Oferta y demanda, elasticidad, estructuras de mercado, indicadores macro | I23: Alta - entorno económico de la decisión empresarial | J23: Baja | K23: Baja | L23: Baja | N23: — | O23: No encaja | P23: Baja | Q23: Cubierto parcialmente por el catálogo; el resto del curso se apoya en SimVenture, SimAgile o SimProject según el caso | R23: SimVenture o Sunny Day / Energy&Co (CompanyGame) | S23: SimVenture permite observar el efecto de precio, demanda y competencia en un mercado simulado. No cubre el contenido macroeconómico del curso, por lo que su rol es de ilustración, no de eje. | T23: Complementario | U23: Media | V23: Inferencia académica
A24: Ingeniería Industrial | B24: Semestre 3 | C24: GESTIÓN ORGANIZACIONAL | D24: 2 | E24: Profesional | F24: Gestión empresarial | G24: Comprensión de la estructura y los procesos administrativos de la organización; liderazgo y toma de decisiones | H24: Teoría organizacional, funciones administrativas, estructura, cultura, liderazgo | I24: Alta - gestión empresarial integral | J24: Baja | K24: Baja | L24: Baja | M24: Business21 | N24: N3-4 | O24: Encaje perfecto | P24: Media | Q24: Cubierto por el catálogo CompanyGame | R24: Business21 (CompanyGame) o SimVenture | S24: El curso trata la organización como sistema de decisiones; SimVenture pone al estudiante a dirigirla. Es una de las asignaturas donde el simulador puede ser eje del curso y no un complemento. Organization & People Management aporta específicamente la dimensión de dirección de personas del curso. | T24: Principal | U24: Alta | V24: Inferencia académica
A25: Ingeniería Industrial | B25: Semestre 3 | C25: ELECTIVA II | D25: 2 | E25: Electiva | F25: Espacio electivo sin contenido definido | G25: No disponible en la fuente | H25: No disponible en la fuente | I25: No determinable con la información disponible | J25: No evaluable | K25: No evaluable | L25: No evaluable | M25: Por definir según el contenido del espacio | N25: — | O25: Por definir | P25: No evaluable | Q25: Depende del contenido que se defina para la electiva u optativa | R25: Depende del contenido de la electiva | S25: Espacio de inserción sin rediseño curricular. Ver Electiva I. | T25: Principal (si se diseña la electiva) | U25: Media | V25: No disponible en la fuente
A26: Ingeniería Industrial | B26: Semestre 4 | C26: ECUACIONES DIFERENCIALES | D26: 3 | E26: Básico | F26: Ciencias básicas | G26: Modelado de sistemas dinámicos | H26: EDO, transformadas, aplicaciones | I26: Nula | J26: Baja | K26: Baja | L26: Baja | M26: — | N26: — | O26: No encaja | P26: Baja | Q26: No requiere simulador — asignatura sin decisiones de gestión, proyecto o negocio | R26: Ninguno | S26: Ciencias básicas sin decisiones empresariales. | T26: No aplica | U26: Baja | V26: Inferencia académica
A27: Ingeniería Industrial | B27: Semestre 4 | C27: TERMODINÁMICA | D27: 3 | E27: Básico | F27: Ciencias básicas de ingeniería | G27: Análisis energético de procesos | H27: Leyes de la termodinámica, ciclos, balance de energía | I27: Baja - eficiencia energética con impacto en costos | J27: Baja | K27: Baja | L27: Baja | M27: — | N27: — | O27: No encaja | P27: Baja | Q27: No requiere simulador — asignatura sin decisiones de gestión, proyecto o negocio | R27: Ninguno | S27: Contenido físico-técnico sin decisiones de gestión. | T27: No aplica | U27: Baja | V27: Inferencia académica
A28: Ingeniería Industrial | B28: Semestre 4 | C28: GERENCIA ESTRATÉGICA | D28: 3 | E28: Profesional | F28: Estrategia y dirección | G28: Análisis del entorno competitivo, formulación e implementación de estrategia, medición del desempeño | H28: Diagnóstico estratégico, ventaja competitiva, direccionamiento, despliegue y control estratégico | I28: Muy alta - núcleo de la dirección de empresas | J28: Alta | K28: Baja | L28: Baja | M28: Business Strategy | N28: N5 / N6-7 | O28: Encaje perfecto | P28: Media | Q28: Cubierto por el catálogo CompanyGame | R28: SimVenture o Businessglobal / Business Strategy (CompanyGame) | S28: Es la asignatura de mayor encaje del programa: el estudiante debe formular una estrategia y sostenerla durante varios períodos frente a competidores, que es precisamente lo que SimVenture obliga a hacer. Permite evaluar la estrategia por resultados y no por presentación. Dentro de CompanyGame, Businessglobal y Business Strategy son las alternativas de mayor nivel para esta asignatura y permiten ofrecer dos opciones de precio en la misma conversación. | T28: Principal | U28: Alta | V28: Inferencia académica
A29: Ingeniería Industrial | B29: Semestre 4 | C29: CONTROL ESTADÍSTICA DE LA CALIDAD | D29: 3 | E29: Profesional | F29: Calidad y mejoramiento | G29: Control y mejora de procesos mediante herramientas estadísticas | H29: Cartas de control, capacidad de proceso, muestreo de aceptación, seis sigma | I29: Media - calidad como variable de gestión operativa | J29: Baja | K29: Baja | L29: Baja | M29: — | N29: — | O29: No encaja | P29: Alta | Q29: DP-06: simulador de control estadístico de procesos con costo de la no calidad | R29: Desarrollo propio (simulador de control de calidad) | S29: Ninguno de los tres simuladores modela control estadístico de procesos. Existe una oportunidad clara de desarrollo propio: un proceso simulado donde el estudiante ajuste parámetros, muestree y vea el costo de la no calidad. | T29: No aplica (hoy) | U29: Media | V29: Inferencia académica
A30: Ingeniería Industrial | B30: Semestre 4 | C30: PROCESOS INDUSTRIALES | D30: 3 | E30: Profesional | F30: Producción y operaciones | G30: Comprensión y selección de procesos de manufactura y transformación | H30: Procesos de manufactura, tecnologías de producción, parámetros de proceso | I30: Media - decisiones de tecnología y capacidad | J30: Baja | K30: Baja | L30: Baja | M30: — | N30: — | O30: No encaja | P30: Alta | Q30: DP-01/DP-09: simulador de planta con selección de procesos y parámetros de producción | R30: Desarrollo propio (simulador de planta) | S30: El contenido es técnico-productivo; ningún simulador del portafolio lo cubre. Es candidato natural a un simulador propio de planta. | T30: No aplica (hoy) | U30: Media | V30: Inferencia académica
A31: Ingeniería Industrial | B31: Semestre 4 | C31: COSTOS DE OPERACIÓN | D31: 3 | E31: Profesional | F31: Gestión financiera | G31: Estructuración y análisis de costos; decisiones basadas en márgenes | H31: Costeo por órdenes y procesos, costeo ABC, punto de equilibrio, costos para la decisión | I31: Alta - los costos son la base de la decisión empresarial | J31: Baja | K31: Baja | L31: Baja | M31: — | N31: — | O31: Encaje parcial | P31: Media | Q31: Cubierto parcialmente por el catálogo; el resto del curso se apoya en SimVenture, SimAgile o SimProject según el caso | R31: SimVenture o ContaTrainer / Kapital (CompanyGame) | S31: En SimVenture cada decisión modifica la estructura de costos y el punto de equilibrio, lo que convierte el costeo en una consecuencia visible y no en un ejercicio de hoja de cálculo. | T31: Complementario | U31: Alta | V31: Inferencia académica
A32: Ingeniería Industrial | B32: Semestre 5 | C32: INVESTIGACIÓN OPERATIVA I | D32: 3 | E32: Profesional | F32: Métodos cuantitativos | G32: Modelado y solución de problemas de optimización con restricciones | H32: Programación lineal, método símplex, dualidad, análisis de sensibilidad | I32: Media - optimiza decisiones de negocio pero desde el método | J32: Baja | K32: Baja | L32: Baja | M32: — | N32: — | O32: No encaja | P32: Alta | Q32: DP-01: simulador de asignación de recursos escasos con restricciones | R32: Desarrollo propio (simulador de decisiones con restricciones) | S32: El curso enseña la técnica de optimización, no la gestión. Un simulador propio que obligue a asignar recursos escasos y ver consecuencias sería pertinente; los tres simuladores actuales no lo cubren. | T32: Exploratorio | U32: Media | V32: Inferencia académica
A33: Ingeniería Industrial | B33: Semestre 5 | C33: SISTEMA INTEGRADO DE GESTIÓN | D33: 2 | E33: Profesional | F33: Calidad y sistemas de gestión | G33: Diseño, implementación y auditoría de sistemas de gestión integrados | H33: ISO 9001, 14001, 45001, gestión por procesos, auditoría, mejora continua | I33: Alta - gestión organizacional por procesos | J33: Baja | K33: Baja | L33: Baja | M33: — | N33: — | O33: No encaja | P33: Alta | Q33: DP-03: simulador de implementación y auditoría de un sistema integrado de gestión | R33: Desarrollo propio (simulador de implementación de SGI) | S33: La implementación de un SGI es un proyecto con alcance, plazos y recursos, lo que da entrada parcial a SimProject. La oportunidad fuerte es un simulador propio de implementación y auditoría, aplicable también a Ing. de Sistemas. ESGManagement cubre parcialmente el componente ambiental y social del sistema integrado de gestión. | T33: Complementario | U33: Media | V33: Inferencia académica
A34: Ingeniería Industrial | B34: Semestre 5 | C34: DISEÑO DE PRODUCTOS Y SERVICIOS | D34: 3 | E34: Profesional | F34: Innovación y desarrollo de producto | G34: Desarrollo de nuevos productos y servicios desde la necesidad del cliente hasta la viabilidad | H34: Voz del cliente, QFD, ciclo de vida del producto, prototipado, viabilidad comercial | I34: Muy alta - innovación, producto y mercado | J34: Baja | K34: Baja | L34: Baja | M34: — | N34: — | O34: No encaja | P34: Media | Q34: Cubierto por el catálogo CompanyGame | R34: SimAgile (principal) + SimVenture o InnovaTech (CompanyGame) | S34: El desarrollo de producto moderno es iterativo y basado en validación, que es el modelo de SimAgile. SimVenture agrega la prueba de viabilidad comercial del producto diseñado. Es la asignatura con doble encaje más claro del programa. InnovaTech es la alternativa CompanyGame más ajustada al desarrollo de nuevos productos con base tecnológica. | T34: Principal | U34: Alta | V34: Inferencia académica
A35: Ingeniería Industrial | B35: Semestre 5 | C35: INGENIERÍA DE MÉTODOS | D35: 3 | E35: Profesional | F35: Producción y operaciones | G35: Análisis y mejora del trabajo; medición de la productividad | H35: Estudio de métodos, estudio de tiempos, balanceo, estandarización | I35: Media - productividad operativa | J35: Baja | K35: Baja | L35: Baja | M35: — | N35: — | O35: No encaja | P35: Alta | Q35: DP-01: simulador de estudio del trabajo, tiempos y productividad de línea | R35: Desarrollo propio (simulador de estudio del trabajo) | S35: Contenido operativo específico no cubierto por el portafolio. Alto potencial de simulador propio de línea de producción con medición de tiempos. | T35: No aplica (hoy) | U35: Media | V35: Inferencia académica
... A57: Ingeniería Industrial | B57: Semestre 8 | C57: OPTATIVA III | D57: 3 | E57: Optativo | F57: Espacio optativo sin contenido definido | G57: No disponible en la fuente | H57: No disponible en la fuente | I57: No determinable con la información disponible | J57: No evaluable | K57: No evaluable | L57: No evaluable | M57: Por definir según el contenido del espacio | N57: — | O57: Por definir | P57: No evaluable | Q57: Depende del contenido que se defina para la electiva u optativa | R57: Depende del contenido de la optativa | S57: Espacio de profundización sin contenido definido. Ver Optativa I. | T57: Principal (si se diseña la optativa) | U57: Media | V57: No disponible en la fuente
A59: Nota: Explícito en la malla → programa, semestre, asignatura, créditos y componente de formación. Inferencia académica → área temática, competencias, temáticas, relación con la gestión y todos los niveles de compatibilidad. Grado de ajuste con el catálogo CompanyGame: Encaje perfecto = el simulador cubre el objeto central del curso; Encaje parcial = cubre una unidad o el contexto; No encaja = ningún simulador del catálogo aplica. Ver hoja 'Catálogo CompanyGame'.

Sheet Ing. de Sistemas
A1: Matriz de relacionamiento – Ingeniería de Sistemas
A2: Universidad Libre – Facultad de Ingeniería · SNIES 11584 · 53 asignaturas · 144 créditos
A4: Programa | B4: Semestre | C4: Asignatura | D4: Créditos | E4: Componente de formación | F4: Área temática | G4: Competencias principales | H4: Temáticas principales | I4: Relación con gestión / negocio | J4: SimVenture | K4: SimAgile | L4: SimProject | M4: Simulador CompanyGame que encaja | N4: Nivel CG | O4: Grado de ajuste | P4: Desarrollo propio | Q4: Tipo de simulador que se requeriría | R4: Simulador recomendado | S4: Justificación de la recomendación | T4: Tipo de uso sugerido | U4: Prioridad comercial | V4: Origen de competencias y temáticas
A5: Ingeniería de Sistemas | B5: Semestre 1 | C5: INTRODUCCIÓN A LA INGENIERÍA | D5: 2 | E5: Básico | F5: Fundamentación profesional | G5: Comprensión del campo de acción del ingeniero de sistemas; trabajo en equipo | H5: Perfil profesional, áreas de la ingeniería de sistemas, rol del ingeniero | I5: Media - contextualización profesional | J5: Baja | K5: Baja | L5: Baja | M5: — | N5: — | O5: No encaja | P5: Media | Q5: Cubierto parcialmente por el catálogo; el resto del curso se apoya en SimVenture, SimAgile o SimProject según el caso | R5: T-Shirt / Sunny Day (CompanyGame, nivel introductorio) | S5: Curso de contextualización sin decisiones de gestión. Un módulo corto puede usarse como actividad motivadora, pero no hay contenido que el simulador cubra. Un simulador de nivel 1-2 funciona como primera experiencia de decisión empresarial en primer semestre, con alto volumen de estudiantes. | T5: Exploratorio | U5: Media | V5: Inferencia académica
A6: Ingeniería de Sistemas | B6: Semestre 1 | C6: LÓGICA Y ALGORITMOS | D6: 3 | E6: Básico | F6: Ciencias básicas de ingeniería | G6: Pensamiento algorítmico y resolución estructurada de problemas | H6: Lógica, diagramas de flujo, pseudocódigo, algoritmos básicos | I6: Nula | J6: Baja | K6: Baja | L6: Baja | M6: — | N6: — | O6: No encaja | P6: Baja | Q6: No requiere simulador — asignatura sin decisiones de gestión, proyecto o negocio | R6: Ninguno | S6: Competencia técnica sin decisiones de gestión. | T6: No aplica | U6: Baja | V6: Inferencia académica
A7: Ingeniería de Sistemas | B7: Semestre 1 | C7: LÓGICA MATEMÁTICA | D7: 3 | E7: Básico | F7: Ciencias básicas | G7: Razonamiento formal y demostración | H7: Lógica proposicional y de predicados, inferencia, demostración | I7: Nula | J7: Baja | K7: Baja | L7: Baja | M7: — | N7: — | O7: No encaja | P7: Baja | Q7: No requiere simulador — asignatura sin decisiones de gestión, proyecto o negocio | R7: Ninguno | S7: Ciencias básicas sin componente de gestión. | T7: No aplica | U7: Baja | V7: Inferencia académica
A8: Ingeniería de Sistemas | B8: Semestre 1 | C8: CÁLCULO DIFERENCIAL | D8: 3 | E8: Básico | F8: Ciencias básicas | G8: Razonamiento matemático, modelado de variación | H8: Límites, derivadas, optimización | I8: Nula | J8: Baja | K8: Baja | L8: Baja | M8: — | N8: — | O8: No encaja | P8: Baja | Q8: No requiere simulador — asignatura sin decisiones de gestión, proyecto o negocio | R8: Ninguno | S8: Ciencias básicas sin decisiones empresariales. | T8: No aplica | U8: Baja | V8: Inferencia académica
A9: Ingeniería de Sistemas | B9: Semestre 1 | C9: FÍSICA MECÁNICA Y LABORATORIO | D9: 3 | E9: Básico | F9: Ciencias básicas | G9: Modelado físico y experimentación | H9: Cinemática, dinámica, energía, laboratorio | I9: Nula para simuladores de gestión | J9: Baja | K9: Baja | L9: Baja | M9: — | N9: — | O9: No encaja | P9: Media | Q9: Laboratorio virtual de física | R9: Desarrollo propio (laboratorio virtual) | S9: Sin relación con simuladores de negocio; oportunidad únicamente en la línea de laboratorios virtuales. | T9: No aplica | U9: Baja | V9: Inferencia académica
A10: Ingeniería de Sistemas | B10: Semestre 1 | C10: CÁTEDRA UNILIBRISTA | D10: 1 | E10: Humanístico | F10: Formación institucional | G10: Identidad institucional y valores unilibristas | H10: Historia, principios y proyecto educativo institucional | I10: Nula | J10: Baja | K10: Baja | L10: Baja | M10: — | N10: — | O10: No encaja | P10: Baja | Q10: No requiere simulador — asignatura sin decisiones de gestión, proyecto o negocio | R10: Ninguno | S10: Cátedra institucional sin contenidos de gestión. | T10: No aplica | U10: Baja | V10: Inferencia académica
A11: Ingeniería de Sistemas | B11: Semestre 1 | C11: COMPETENCIAS DE APRENDIZAJE Y COMUNICACIÓN | D11: 3 | E11: Humanístico | F11: Formación humanística | G11: Comunicación oral y escrita, lectura crítica, trabajo colaborativo | H11: Competencias comunicativas, argumentación, trabajo en equipo | I11: Baja | J11: Baja | K11: Baja | L11: Baja | M11: — | N11: — | O11: No encaja | P11: Baja | Q11: No requiere simulador — asignatura sin decisiones de gestión, proyecto o negocio | R11: Ninguno | S11: Desarrolla trabajo en equipo pero sin contenido de gestión que justifique un simulador. | T11: No aplica | U11: Baja | V11: Inferencia académica
A12: Ingeniería de Sistemas | B12: Semestre 2 | C12: CÁLCULO INTEGRAL | D12: 3 | E12: Básico | F12: Ciencias básicas | G12: Razonamiento matemático, integración | H12: Integrales, aplicaciones, series | I12: Nula | J12: Baja | K12: Baja | L12: Baja | M12: — | N12: — | O12: No encaja | P12: Baja | Q12: No requiere simulador — asignatura sin decisiones de gestión, proyecto o negocio | R12: Ninguno | S12: Ciencias básicas sin decisiones empresariales. | T12: No aplica | U12: Baja | V12: Inferencia académica
A13: Ingeniería de Sistemas | B13: Semestre 2 | C13: ELECTIVA I | D13: 2 | E13: Electiva | F13: Espacio electivo sin contenido definido | G13: No disponible en la fuente | H13: No disponible en la fuente | I13: No determinable con la información disponible | J13: No evaluable | K13: No evaluable | L13: No evaluable | M13: Por definir según el contenido del espacio | N13: — | O13: Por definir | P13: No evaluable | Q13: Depende del contenido que se defina para la electiva u optativa | R13: Depende del contenido de la electiva | S13: La malla no define contenido. Comercialmente es el espacio de inserción más rápido: permite proponer una electiva completa basada en simulador sin modificar el plan de estudios. | T13: Principal (si se diseña la electiva) | U13: Media | V13: No disponible en la fuente
A14: Ingeniería de Sistemas | B14: Semestre 2 | C14: ALGEBRA LINEAL | D14: 3 | E14: Básico | F14: Ciencias básicas | G14: Modelado matricial y solución de sistemas | H14: Matrices, vectores, espacios, transformaciones | I14: Nula | J14: Baja | K14: Baja | L14: Baja | M14: — | N14: — | O14: No encaja | P14: Baja | Q14: No requiere simulador — asignatura sin decisiones de gestión, proyecto o negocio | R14: Ninguno | S14: Ciencias básicas sin decisiones empresariales. | T14: No aplica | U14: Baja | V14: Inferencia académica
A15: Ingeniería de Sistemas | B15: Semestre 2 | C15: FUNDAMENTOS DE PROGRAMACIÓN | D15: 3 | E15: Básico | F15: Desarrollo de software | G15: Programación estructurada, resolución de problemas mediante código | H15: Tipos de datos, estructuras de control, funciones, depuración | I15: Nula | J15: Baja | K15: Baja | L15: Baja | M15: — | N15: — | O15: No encaja | P15: Baja | Q15: No requiere simulador — asignatura sin decisiones de gestión, proyecto o negocio | R15: Ninguno | S15: Competencia técnica individual; no hay decisiones de gestión ni dinámica de equipo formalizada. | T15: No aplica | U15: Baja | V15: Inferencia académica
A16: Ingeniería de Sistemas | B16: Semestre 2 | C16: PENSAMIENTO SISTÉMICO | D16: 2 | E16: Profesional | F16: Pensamiento sistémico y organización | G16: Análisis de sistemas complejos, comprensión de interdependencias y efectos de segundo orden | H16: Teoría general de sistemas, causalidad circular, dinámica de sistemas, visión holística de la organización | I16: Alta - la organización entendida como sistema de decisiones interdependientes | J16: Baja | K16: Baja | L16: Baja | M16: Business21 | N16: N3-4 | O16: Encaje perfecto | P16: Alta | Q16: Cubierto por Business21 y SimVenture; opcional un simulador de dinámica de sistemas | R16: SimVenture o Business21 (CompanyGame) | S16: Es el curso donde el simulador de empresa tiene su justificación pedagógica más pura: el estudiante comprueba que una decisión en un área altera el resultado de otra, lo que un caso escrito no puede mostrar. Argumento fácil de sostener ante el docente. Business21 tiene el nivel adecuado para una asignatura de segundo semestre y resulta más económico que un simulador de nivel superior. | T16: Principal | U16: Alta | V16: Inferencia académica
... A57: Ingeniería de Sistemas | B57: Semestre 8 | C57: OPTATIVA III | D57: 3 | E57: Optativo | F57: Espacio optativo sin contenido definido | G57: No disponible en la fuente | H57: No disponible en la fuente | I57: No determinable con la información disponible | J57: No evaluable | K57: No evaluable | L57: No evaluable | M57: Por definir según el contenido del espacio | N57: — | O57: Por definir | P57: No evaluable | Q57: Depende del contenido que se defina para la electiva u optativa | R57: Depende del contenido de la optativa | S57: Espacio de profundización sin contenido definido. Ver Optativa I. | T57: Principal (si se diseña la optativa) | U57: Media | V57: No disponible en la fuente
A59: Nota: Explícito en la malla → programa, semestre, asignatura, créditos y componente de formación. Inferencia académica → área temática, competencias, temáticas, relación con la gestión y todos los niveles de compatibilidad. Grado de ajuste con el catálogo CompanyGame: Encaje perfecto = el simulador cubre el objeto central del curso; Encaje parcial = cubre una unidad o el contexto; No encaja = ningún simulador del catálogo aplica. Ver hoja 'Catálogo CompanyGame'.

Sheet Priorización
A1: Priorización comercial de oportunidades
A2: Ranking de asignaturas con mayor potencial de implementación · Top 15 y bloque de siguiente nivel · incluye alternativa del catálogo CompanyGame
A4: Ranking | B4: Bloque | C4: Programa | D4: Semestre | E4: Asignatura | F4: Simulador recomendado | G4: Simulador CompanyGame que encaja | H4: ¿Por qué es una oportunidad? | I4: Competencia académica que se fortalece | J4: Valor diferencial que aporta el simulador | K4: Facilidad de justificación | L4: Argumento para la conversación comercial
A5: 1 | B5: Top 15 | C5: Ing. de Sistemas | D5: Semestre 7 | E5: GESTIÓN DE PROYECTOS DE INGENIERÍA | F5: SimProject | G5: Acelera; ESGProject (gestión de un proyecto acotado) | H5: El temario de dirección de proyectos coincide punto por punto con las decisiones que exige el simulador: alcance, cronograma, recursos, costos, riesgos y control. | I5: Dirección y control de proyectos de ingeniería | J5: Sustituye el ejercicio de cronograma en papel por la ejecución de un proyecto con desviaciones reales, replanificación y consecuencias medibles. | K5: Alta | L5: No requiere modificar el programa: el simulador se convierte en el taller práctico del curso. Es la conversación más corta de todo el portafolio.
A6: 2 | B6: Top 15 | C6: Ing. Industrial | D6: Semestre 4 | E6: GERENCIA ESTRATÉGICA | F6: SimVenture | G6: Businessglobal (Nivel 5) o Business Strategy (Niveles 6 y 7) | H6: Asignatura de estrategia con 3 créditos donde el estudiante debe formular y sostener una estrategia en el tiempo, algo que un caso escrito no permite evaluar. | I6: Formulación e implementación de estrategia competitiva | J6: La estrategia se evalúa por resultados sostenidos frente a competidores y no por la calidad de una presentación. | K6: Alta | L6: El argumento es directo: hoy la estrategia se evalúa por documento; con el simulador se evalúa por desempeño. Fácil de defender ante el director de programa.
A7: 3 | B7: Top 15 | C7: Ing. Industrial | D7: Semestre 7 | E7: FORMULACIÓN Y EVALUACIÓN DE PROYECTOS | F7: SimVenture + SimProject | G7: FitnessGym, Luxe Atelier (Niveles 3 y 4); Business Chef (Nivel 5); ESGProject | H7: Única asignatura del programa con encaje alto simultáneo en dos simuladores: formulación del negocio y gestión del proyecto. | I7: Formulación, evaluación y gestión de proyectos | J7: Cubre el ciclo completo: viabilidad de mercado y financiera con SimVenture, y planeación y control de la ejecución con SimProject. | K7: Alta | L7: Permite proponer un paquete de dos productos en un solo curso, con justificación académica en dos mitades claramente diferenciadas del programa.
A8: 4 | B8: Top 15 | C8: Ing. de Sistemas | D8: Semestre 5 | E8: INGENIERÍA DEL SOFTWARE III | F8: SimAgile + SimProject | G8: Organization & People Management; InnovaTech | H8: Es el curso de gestión de la línea de software: planeación, estimación, métricas, riesgos y gestión de equipos. | I8: Gestión de proyectos y equipos de desarrollo de software | J8: El estudiante experimenta la tensión entre alcance, calidad y tiempo dentro de un equipo, en lugar de estudiarla en teoría. | K8: Alta | L8: Doble encaje en un mismo curso; el docente de esta asignatura suele ser también el de Gestión de Proyectos, lo que concentra la decisión en un solo interlocutor.
A9: 5 | B9: Top 15 | C9: Ing. Industrial | D9: Semestre 6 | E9: FINANZAS | F9: SimVenture | G9: Kapital (Nivel 5); Bankgame; BANKCOMPANY (Niveles 6 y 7) | H9: Asignatura de decisión financiera donde el simulador genera los estados financieros a partir de las decisiones del propio estudiante. | I9: Diagnóstico financiero y decisiones de inversión y financiación | J9: El análisis financiero deja de hacerse sobre datos ajenos y pasa a hacerse sobre las consecuencias de decisiones propias. | K9: Alta | L9: Argumento pedagógico muy claro; además es una asignatura con alto índice de reprobación en programas de ingeniería, lo que abre la conversación por el lado de la retención.
A10: 6 | B10: Top 15 | C10: Ambos programas | D10: Semestre V (Ind.) / IV (Sist.) | E10: CÁTEDRA DE SOSTENIBILIDAD | F10: ESGManagement / ESGProject (CompanyGame) | G10: ESGManagement (Nivel 5); ESGProject (Niveles 3 y 4); GlobalManagement | H10: Asignatura obligatoria en los dos programas que hoy no tiene ninguna herramienta práctica asociada, y cuyo objeto completo está cubierto por la familia ESG Management del catálogo CompanyGame. | I10: Comprensión y gestión de la sostenibilidad aplicada a la organización | J10: Convierte una cátedra hoy discursiva en una experiencia de decisión donde el estudiante enfrenta el trade-off entre resultado económico e impacto ambiental y social. | K10: Alta | L10: Es la mejor relación esfuerzo-resultado del catálogo: una sola conversación cubre dos programas, y la asignatura no compite con ningún recurso existente porque hoy no usa ninguno.
A11: 7 | B11: Top 15 | C11: Ing. de Sistemas | D11: Semestre 6 | E11: FORMULACIÓN Y EVALUACIÓN DE PROYECTOS | F11: SimProject + SimVenture | G11: FitnessGym, Luxe Atelier (Niveles 3 y 4); Business Chef (Nivel 5); ESGProject | H11: Mismo encaje doble que en Ing. Industrial, en un programa donde el estudiante tiene menos formación previa en negocio. | I11: Formulación y evaluación de la viabilidad de proyectos | J11: Aporta al ingeniero de sistemas la dimensión de mercado y financiera que su formación técnica no cubre. | K11: Alta | L11: Se puede presentar como la misma solución ya conversada con Ing. Industrial, lo que reduce el esfuerzo de venta a nivel de facultad.
A12: 8 | B12: Top 15 | C12: Ing. Industrial | D12: Semestre 6 | E12: MERCADEO | F12: SimVenture | G12: MarketGame; SalesManager; GlobalMARKET; FOCUS (Niveles 6 y 7) | H12: Asignatura comercial de 3 créditos donde precio, promoción y canal pueden competir en un mercado simulado. | I12: Diseño y ejecución de la estrategia comercial | J12: El resultado comercial se mide en ventas y participación de mercado frente a competidores reales del aula. | K12: Alta | L12: Es la aplicación más reconocible de un simulador de negocios; casi no requiere explicación previa.
A13: 9 | B13: Top 15 | C13: Ing. de Sistemas | D13: Semestre 4 | E13: INGENIERÍA DE SOFTWARE II | F13: SimAgile | G13: Organization & People Management (gestión del equipo de desarrollo) | H13: El curso combina diseño técnico con gestión del proceso de desarrollo y trabajo en equipo. | I13: Gestión del proceso de desarrollo y trabajo colaborativo | J13: Convierte las ceremonias ágiles en una experiencia con consecuencias, en lugar de un contenido memorizado. | K13: Alta | L13: El docente de ingeniería de software suele estar familiarizado con marcos ágiles; la conversación parte de un lenguaje común.
A14: 10 | B14: Top 15 | C14: Ing. Industrial | D14: Semestre 5 | E14: DISEÑO DE PRODUCTOS Y SERVICIOS | F14: SimAgile + SimVenture | G14: InnovaTech (Niveles 3 y 4); TechCompany / Food Company | H14: Desarrollo de nuevos productos con validación de viabilidad: encaje doble poco frecuente en un programa de industrial. | I14: Innovación y desarrollo de productos y servicios | J14: Une la iteración del desarrollo con la prueba comercial del producto, cerrando el ciclo idea-mercado dentro del aula. | K14: Alta | L14: Permite introducir SimAgile en Ingeniería Industrial, un programa donde normalmente sólo se conversa sobre SimVenture.
A15: 11 | B15: Top 15 | C15: Ing. de Sistemas | D15: Semestre 8 | E15: ARQUITECTURA EMPRESARIAL | F15: SimAgile + SimVenture | G15: TRANSFORMA; Global2030 (Niveles 6 y 7); Acelera | H15: Asignatura bisagra entre negocio y tecnología, con contenido explícito de transformación digital. | I15: Alineación entre estrategia de negocio y arquitectura tecnológica | J15: Da al estudiante la comprensión del negocio que la arquitectura debe soportar, que es justamente lo que su formación técnica no entrega. | K15: Media | L15: Requiere explicar por qué un simulador de empresa aporta a una asignatura técnica; el argumento es fuerte pero necesita una demostración.
A16: 12 | B16: Top 15 | C16: Ing. Industrial | D16: Semestre 6 | E16: GESTIÓN DE TECNOLOGÍA | F16: SimAgile | G16: InnovaTech; TRANSFORMA; Global2030 (Niveles 6 y 7); Acelera | H16: Contenido explícito de innovación y transformación digital en un programa de ingeniería industrial. | I16: Gestión de la innovación y de la incorporación tecnológica | J16: Traduce la gestión de la innovación en decisiones concretas de priorización y entrega, no en un marco teórico. | K16: Alta | L16: Es la puerta natural de SimAgile en Ingeniería Industrial y complementa la conversación de SimVenture con el mismo director.
... A27: 23 | B27: Siguiente nivel | C27: Ing. Industrial | D27: Semestre 2 | E27: CONTABILIDAD Y PRESUPUESTO | F27: SimVenture | G27: ContaTrainer (Niveles 1 a 2); Business21 (Niveles 3 y 4) | H27: El simulador genera estados financieros y presupuestos como resultado de las decisiones del estudiante. | I27: Interpretación de estados financieros y control presupuestal | J27: Reemplaza los casos estáticos por información contable derivada de decisiones propias. | K27: Media | L27: Asignatura de 2 créditos en segundo semestre; conviene incluirla dentro de un acuerdo de programa y no venderla sola.
A29: Criterio de ordenamiento: nivel de encaje con el temario (Alta > Media), existencia de producto listo para usar, facilidad de justificación académica ante el docente o director, número de créditos y volumen de estudiantes, y cercanía al perfil de egreso.

Sheet Desarrollos Propios
A1: Oportunidades de desarrollo propio de simuladores
A2: Asignaturas sin cobertura de SimVenture, SimAgile, SimProject ni del catálogo CompanyGame, priorizadas por transversalidad
A4: Código | B4: Simulador propuesto | C4: Programa(s) | D4: Asignaturas destino | E4: Problema o necesidad académica que resuelve | F4: Temática que debería simular | G4: Decisiones que debería permitir tomar al estudiante | H4: Competencias que permitiría desarrollar | I4: Por qué conviene un desarrollo propio y no un simulador del portafolio actual | J4: Transversalidad | K4: Prioridad
A5: DP-01 | B5: Simulador de Planeación y Control de Operaciones | C5: Ing. Industrial | D5: PLANEACIÓN Y CONTROL DE LA PRODUCCIÓN Y OPERACIONES (VI); INVESTIGACIÓN OPERATIVA I (V); INVESTIGACIÓN OPERATIVA II (VI); INGENIERÍA DE MÉTODOS (V); SIMULACIÓN DE PROCESOS (VIII); DISEÑO DE INSTALACIONES INDUSTRIALES Y DE SERVICIOS (VIII) | E5: El núcleo profesional del programa (producción y operaciones) no tiene ningún simulador asociado; se enseña con ejercicios numéricos aislados que no muestran el efecto acumulado de las decisiones a lo largo del tiempo. | F5: Una planta de producción con demanda variable: pronóstico, plan maestro, explosión de materiales, capacidad, inventarios y programación de la producción. | G5: Nivel de producción por período; tamaño de lote; contratación y turnos; nivel de inventario de seguridad; subcontratación; prioridad de órdenes; inversión en capacidad. | H5: Planeación agregada; programación de la producción; gestión de inventarios; análisis del trade-off costo-nivel de servicio; toma de decisiones bajo demanda incierta. | I5: SimVenture modela producción de forma agregada y simplificada, muy por debajo del nivel exigido por el curso. SimProject y SimAgile no aplican. Es el mayor vacío del portafolio frente a la malla de Ingeniería Industrial. | J5: Alta - 6 asignaturas de un programa | K5: Prioridad 1
A6: DP-02 | B6: Simulador de Transformación Digital y Arquitectura Empresarial | C6: Ing. de Sistemas + Ing. Industrial | D6: ARQUITECTURA EMPRESARIAL (VIII, Sistemas); INTELIGENCIA ARTIFICIAL (VII, Sistemas); ARQUITECTURA DE INFORMACIÓN (VI, Sistemas); PENSAMIENTO SISTÉMICO (II, Sistemas); GESTIÓN DE TECNOLOGÍA (VI, Industrial); GERENCIA ESTRATÉGICA (IV Industrial / VIII Sistemas) | E6: La transformación digital se enseña como marco conceptual (capacidades, hojas de ruta, gobierno de TI) sin ninguna experiencia de decisión. Es además el tema con mayor visibilidad institucional actual. | F6: Una organización que debe modernizar sus capacidades: priorización de iniciativas, deuda técnica, adopción de IA, gestión del cambio y retorno de la inversión tecnológica. | G6: Qué capacidades intervenir primero; comprar vs. construir; nivel de inversión en infraestructura y datos; ritmo de adopción de IA; manejo de la resistencia al cambio; indicadores de éxito. | H6: Alineación negocio-tecnología; priorización de portafolio tecnológico; gestión del cambio; evaluación del retorno de la inversión en TI; gobierno de datos e IA. | I6: REVISADO CON EL CATÁLOGO COMPANYGAME: la familia Business Transformation (TRANSFORMA, Global2030, Acelera, InnovaTech) ya cubre buena parte de este terreno, por lo que un desarrollo propio deja de ser prioritario. La recomendación es ofrecer primero esos simuladores y explorar el desarrollo propio sólo si el programa exige un modelo específico de arquitectura empresarial, gobierno de datos y adopción de IA que esos productos no incluyan. | J6: Alta en asignaturas (6 en los dos programas), pero ya cubierta parcialmente por el catálogo | K6: Prioridad 3 (cubierto parcialmente por CompanyGame)
A7: DP-03 | B7: Simulador de Implementación y Auditoría de Sistemas Integrados de Gestión | C7: Ing. Industrial + Ing. de Sistemas | D7: SISTEMA INTEGRADO DE GESTIÓN (V, Industrial); SISTEMAS INTEGRADOS DE GESTIÓN (VIII, Sistemas); CONTROL ESTADÍSTICA DE LA CALIDAD (IV, Industrial); SEGURIDAD Y SALUD EN EL TRABAJO (VII, Industrial); SEGURIDAD DE LA INFORMACIÓN (VII, Sistemas) | E7: Los sistemas de gestión se enseñan leyendo la norma. El estudiante no experimenta el costo, la resistencia interna ni el resultado de una auditoría. | F7: Implementación de un sistema integrado de gestión en una organización: diagnóstico, documentación, capacitación, auditoría interna y certificación. | G7: Qué procesos documentar primero; presupuesto y equipo asignado; profundidad de la capacitación; tratamiento de no conformidades; momento de solicitar la certificación. | H7: Gestión por procesos; planeación de la implementación; auditoría interna; mejora continua; gestión de no conformidades y del riesgo. | I7: Ninguno de los tres simuladores modela normas de gestión ni procesos de auditoría, y del catálogo CompanyGame sólo ESGManagement toca de forma parcial la dimensión ambiental y social. SimProject aportaría cronograma y costo, dejando fuera el contenido normativo, que es el núcleo del curso. | J7: Alta - 5 asignaturas en los dos programas | K7: Prioridad 1
A8: DP-04 | B8: Simulador de Cadena de Suministro - Simulador GlobalChain | C8: Ing. Industrial | D8: LOGÍSTICA Y CADENA DE SUMINISTRO (VIII); PLANEACIÓN Y CONTROL DE LA PRODUCCIÓN Y OPERACIONES (VI); INVESTIGACIÓN OPERATIVA II (VI); COSTOS DE OPERACIÓN (IV) | E8: La cadena de suministro exige comprender el efecto látigo y la coordinación entre eslabones, algo que no se puede enseñar con ejercicios individuales de inventario. | F8: Una cadena de varios eslabones con demanda variable, tiempos de entrega y costos de faltante y de mantenimiento de inventario. | G8: Cantidad y momento de pedido; selección de proveedores; nivel de servicio objetivo; modo de transporte; grado de información compartida entre eslabones. | H8: Gestión de inventarios; coordinación de la cadena; análisis del trade-off costo-servicio; negociación con proveedores; decisión bajo información incompleta. | I8: SimVenture y Businessglobal incluyen compras e inventarios de forma agregada dentro de una sola empresa; ninguno modela la cadena ni la interacción entre eslabones, que es el aprendizaje central del curso. | J8: Alta - 4 asignaturas de un programa | K8: Prioridad 2
A9: DP-05 | B9: Simulador de Gestión de Incidentes de Seguridad de la Información | C9: Ing. de Sistemas | D9: SEGURIDAD DE LA INFORMACIÓN (VII); SISTEMAS INTEGRADOS DE GESTIÓN (VIII); REDES DE COMPUTADORES (VI) | E9: La seguridad se enseña desde el control y la norma, sin experiencia de decisión bajo presión de tiempo ante un incidente real. | F9: Una organización que sufre incidentes de seguridad: detección, contención, comunicación, recuperación y aprendizaje posterior. | G9: Nivel de inversión en controles preventivos vs. de detección; a quién y cuándo comunicar; aislar o mantener el servicio; pagar o no un rescate; prioridad de recuperación. | H9: Análisis y tratamiento del riesgo; respuesta a incidentes; continuidad del negocio; comunicación de crisis; evaluación costo-beneficio de controles. | I9: Ningún simulador del portafolio aborda seguridad. El tema tiene alta demanda institucional y prácticamente no hay oferta local en español, lo que lo hace muy defendible comercialmente. | J9: Media - 3 asignaturas de un programa | K9: Prioridad 2
A10: DP-06 | B10: Simulador de Control Estadístico de Procesos y Calidad | C10: Ing. Industrial | D10: CONTROL ESTADÍSTICA DE LA CALIDAD (IV); MODELOS MATEMÁTICOS ESTOCÁSTICOS (VII); PROBABILIDAD Y ESTADÍSTICA DESCRIPTIVA (III) | E10: El control estadístico se enseña sobre series de datos ya dadas; el estudiante nunca decide cuándo intervenir un proceso ni asume el costo de equivocarse. | F10: Un proceso productivo con variabilidad natural y causas asignables: muestreo, cartas de control, capacidad y costo de la no calidad. | G10: Tamaño y frecuencia del muestreo; cuándo intervenir el proceso; ajuste de parámetros; nivel de inspección; inversión en mejora del proceso. | H10: Control estadístico de procesos; interpretación de cartas de control; análisis de capacidad; decisión bajo variabilidad; costeo de la calidad. | I10: Ningún simulador de gestión, ni del portafolio propio ni del catálogo CompanyGame, modela variabilidad de proceso. Es un desarrollo acotado y de complejidad media, apto como segundo desarrollo. | J10: Media - 3 asignaturas de un programa | K10: Prioridad 2
A11: DP-07 | B11: Simulador de Dilemas Éticos y Sostenibilidad en la Decisión Profesional | C11: Ing. Industrial + Ing. de Sistemas | D11: ÉTICA (VII, ambos programas); CÁTEDRA DE SOSTENIBILIDAD (V Industrial / IV Sistemas); INTELIGENCIA ARTIFICIAL (VII, Sistemas) | E11: La ética y la sostenibilidad se enseñan de forma discursiva; no hay instrumento que muestre la consecuencia de una decisión cuestionable en el tiempo. | F11: Decisiones profesionales con tensión entre resultado económico, impacto ambiental y consecuencias éticas, incluida la ética en el uso de datos e IA. | G11: Aceptar o rechazar prácticas rentables pero cuestionables; nivel de transparencia; inversión en mitigación de impacto; uso de datos personales; reporte de un hallazgo incómodo. | H11: Razonamiento ético aplicado; análisis de impacto; responsabilidad profesional; comunicación de decisiones difíciles. | I11: REVISADO CON EL CATÁLOGO COMPANYGAME: la dimensión de sostenibilidad ya está cubierta por la familia ESG Management (ESGProject, ESGManagement, GlobalManagement), que debe ofrecerse primero. El desarrollo propio queda acotado al dilema ético profesional y a la ética de datos e IA, que ningún producto del portafolio aborda. | J11: Media - queda acotado a ÉTICA (ambos programas) e INTELIGENCIA ARTIFICIAL | K11: Prioridad 3
A12: DP-08 | B12: Simulador de Seguridad y Salud en el Trabajo (SG-SST) | C12: Ing. Industrial | D12: SEGURIDAD Y SALUD EN EL TRABAJO (VII); SISTEMA INTEGRADO DE GESTIÓN (V) | E12: El SG-SST se enseña desde la normatividad; el estudiante no experimenta la gestión del riesgo laboral ni la investigación de un accidente. | F12: Una operación industrial con riesgos laborales: identificación, valoración, controles, capacitación y ocurrencia de incidentes. | G12: Priorización de controles; inversión en prevención; frecuencia de capacitación; respuesta e investigación ante un accidente; indicadores a reportar. | H12: Identificación y valoración de riesgos; jerarquía de controles; investigación de accidentes; cultura de seguridad. | I12: No cubierto por el portafolio; ESGManagement sólo roza la dimensión social. Dominio muy específico, alcance limitado a dos asignaturas de un programa, pero con demanda potencial fuera del ámbito universitario (formación empresarial). | J12: Baja - 2 asignaturas de un programa | K12: Prioridad 3
A13: DP-09 | B13: Simulador de Diseño de Instalaciones y Procesos Industriales | C13: Ing. Industrial | D13: DISEÑO DE INSTALACIONES INDUSTRIALES Y DE SERVICIOS (VIII); PROCESOS INDUSTRIALES (IV); INGENIERÍA DE MÉTODOS (V) | E13: El diseño de planta se evalúa sobre planos estáticos; el estudiante no ve el desempeño de su distribución en operación. | F13: Distribución en planta y flujo de materiales: localización de estaciones, manejo de materiales, cuellos de botella y capacidad. | G13: Ubicación de estaciones y almacenes; recorrido del material; inversión en equipos de manejo; dimensionamiento de la capacidad. | H13: Distribución en planta; análisis de flujo; identificación de cuellos de botella; dimensionamiento de capacidad. | I13: No cubierto por el portafolio. Requiere componente visual y de simulación de flujo, por lo que su costo de desarrollo es alto frente a su transversalidad. | J13: Media - 3 asignaturas de un programa | K13: Prioridad 3
A14: DP-10 | B14: Línea de laboratorios virtuales (producto distinto a simuladores de gestión) | C14: Ing. Industrial + Ing. de Sistemas | D14: QUÍMICA GENERAL Y LABORATORIO (I, Industrial); FÍSICA MECÁNICA Y LABORATORIO (I/II, ambos); ELECTRICIDAD Y MAGNETISMO Y LABORATORIO (III Industrial / II Sistemas); CIENCIA DE LOS MATERIALES EN LA INDUSTRIA (II, Industrial); ELECTRÓNICA DIGITAL (II, Sistemas) | E14: Las asignaturas con laboratorio dependen de infraestructura física, insumos y disponibilidad de espacio, con limitaciones de cupo y de repetición de la práctica. | F14: Prácticas experimentales de química, física, electricidad, materiales y electrónica digital. | G14: Montaje experimental; variación de parámetros; repetición de mediciones; interpretación de resultados. | H14: Competencia experimental; manejo de instrumentos; análisis de datos experimentales. | I14: Se registra por completitud del análisis: no es una oportunidad para SimVenture, SimAgile ni SimProject, sino para una línea de producto distinta. El interlocutor y el presupuesto son diferentes a los de simuladores de gestión. | J14: Alta en número de asignaturas (5), pero corresponde a otra línea de producto | K14: Fuera del alcance de simuladores de gestión
A16: Criterio de priorización: número de asignaturas y programas a los que aplica el mismo desarrollo (transversalidad), ausencia de cobertura en SimVenture, SimAgile, SimProject y en las siete familias del catálogo CompanyGame, y facilidad de argumentación académica.

Sheet Recomendaciones
A1: Ruta de implementación y recomendaciones estratégicas
A2: Insumo para la conversación con directores de programa, decano y docentes de la Facultad de Ingeniería
A4: Conclusiones por programa – Ing. Industrial
A5: SimVenture | B5: Es el simulador con mayor recorrido en el programa. Encaje alto en GERENCIA ESTRATÉGICA (IV), FINANZAS (VI), MERCADEO (VI), INGENIERÍA ECONÓMICA (V), COSTOS DE OPERACIÓN (IV), GESTIÓN ORGANIZACIONAL (III), CONTABILIDAD Y PRESUPUESTO (II), DISEÑO DE PRODUCTOS Y SERVICIOS (V) y FORMULACIÓN Y EVALUACIÓN DE PROYECTOS (VII). La línea de gestión empresarial del programa está distribuida entre los semestres II y VII, lo que permite proponer un uso continuo y no una compra puntual.
A6: SimAgile | B6: Encaje más acotado pero claro en DISEÑO DE PRODUCTOS Y SERVICIOS (V), GESTIÓN DE TECNOLOGÍA (VI) y DISEÑO EN INGENIERÍA (III). El programa no tiene una línea de metodologías ágiles explícita, por lo que la venta debe apoyarse en el desarrollo de producto y en la innovación tecnológica, no en Scrum como marco.
A7: SimProject | B7: Encaje alto en FORMULACIÓN Y EVALUACIÓN DE PROYECTOS (VII), INGENIERÍA APLICADA (VIII) e INVESTIGACIÓN OPERATIVA II (VI, unidad de PERT/CPM). El programa no tiene una asignatura dedicada exclusivamente a dirección de proyectos, a diferencia de Ing. de Sistemas, por lo que SimProject entra como complemento de asignaturas integradoras.
A8: Desarrollos propios | B8: Aquí está la mayor oportunidad de expansión: toda la línea de producción y operaciones (PLANEACIÓN Y CONTROL DE LA PRODUCCIÓN, INGENIERÍA DE MÉTODOS, PROCESOS INDUSTRIALES, DISEÑO DE INSTALACIONES, LOGÍSTICA, INVESTIGACIÓN OPERATIVA I y II, SIMULACIÓN DE PROCESOS) carece de simulador. Son 8 asignaturas del componente profesional sin cobertura del portafolio actual.
A9: Catálogo CompanyGame | B9: Familias con encaje Alta: Negocios y estrategia (GERENCIA ESTRATÉGICA, GESTIÓN ORGANIZACIONAL), Finanzas y banca (CONTABILIDAD Y PRESUPUESTO con ContaTrainer, FINANZAS con Kapital), Marketing y ventas (MERCADEO), Business Transformation (GESTIÓN DE TECNOLOGÍA, DISEÑO DE PRODUCTOS Y SERVICIOS con InnovaTech) y ESG Management (CÁTEDRA DE SOSTENIBILIDAD). La familia Emprendimiento no tiene asignatura destino porque la malla no incluye creación de empresa, y la familia HORECA no aplica a este programa. El escalonamiento por niveles del catálogo (T-Shirt en I, Business21 en III-IV, Businessglobal en VI-VIII) permite proponer una ruta de varios años y no una venta puntual.
A10: Áreas curriculares con mayor potencial | B10: 1) Gestión empresarial y financiera (semestres II a VII): la más madura para venta inmediata. 2) Proyectos e integración profesional (semestres VII y VIII). 3) Producción y operaciones (semestres IV a VIII): sin cobertura hoy, es el destino natural de un desarrollo propio. La asignatura SIMULACIÓN DE PROCESOS (VIII) merece atención especial: allí la simulación ya está aceptada metodológicamente, lo que la convierte en la mejor puerta de entrada académica al programa.
A12: Conclusiones por programa – Ing. de Sistemas
A13: SimVenture | B13: Encaje alto en GERENCIA ESTRATÉGICA (VIII), PENSAMIENTO SISTÉMICO (II), ARQUITECTURA EMPRESARIAL (VIII) y FORMULACIÓN Y EVALUACIÓN DE PROYECTOS (VI). El programa tiene pocos espacios de gestión empresarial, pero son estratégicos: cubren precisamente la brecha de visión de negocio que se le reconoce al egresado de sistemas. Ese es el argumento de venta, no la cantidad de asignaturas.
A14: SimAgile | B14: Es el simulador de mayor potencial en este programa. Encaje alto en INGENIERÍA DE SOFTWARE I (III), II (IV) y III (V), ARQUITECTURA EMPRESARIAL (VIII) e INGENIERÍA APLICADA (VIII). La línea de ingeniería de software atraviesa cuatro semestres consecutivos, lo que permite proponer un uso escalonado y creciente en lugar de una licencia puntual.
A15: SimProject | B15: GESTIÓN DE PROYECTOS DE INGENIERÍA (VII) es el encaje más directo de todo el análisis: el temario coincide con las decisiones del simulador. Se suma INGENIERÍA DEL SOFTWARE III (V), FORMULACIÓN Y EVALUACIÓN DE PROYECTOS (VI) e INGENIERÍA APLICADA (VIII). Es la conversación comercial que menos argumentación requiere.
A16: Desarrollos propios | B16: Las dos oportunidades más diferenciadoras son el simulador de transformación digital y arquitectura empresarial (ARQUITECTURA EMPRESARIAL, INTELIGENCIA ARTIFICIAL, ARQUITECTURA DE INFORMACIÓN) y el simulador de gestión de incidentes de seguridad de la información (SEGURIDAD DE LA INFORMACIÓN). Ambos temas tienen alta visibilidad institucional y poca o ninguna oferta comparable en español.
A17: Catálogo CompanyGame | B17: Familias con encaje Alta: Negocios y estrategia (GERENCIA ESTRATÉGICA, PENSAMIENTO SISTÉMICO), Business Transformation (ARQUITECTURA EMPRESARIAL con TRANSFORMA y Global2030) y ESG Management (CÁTEDRA DE SOSTENIBILIDAD). Las familias Marketing y ventas, Finanzas y banca y HORECA no tienen asignatura destino en esta malla y no deben ofrecerse. El catálogo no incluye un simulador de dirección de proyectos, por lo que en GESTIÓN DE PROYECTOS DE INGENIERÍA la recomendación sigue siendo SimProject.
A18: Áreas curriculares con mayor potencial | B18: 1) Ingeniería de software y gestión de proyectos (semestres III a VII): la línea más fuerte y de venta más sencilla. 2) Negocio y estrategia (semestres II y VIII): pocos espacios pero de alto valor. 3) Seguridad, IA y arquitectura empresarial (semestres VII y VIII): sin cobertura hoy, destino de los desarrollos propios. El componente técnico de programación, bases de datos, redes y sistemas operativos no ofrece oportunidades y no debe forzarse.
A20: Lectura del catálogo CompanyGame frente a estas dos mallas
A21: Negocios y estrategia | B21: Gestión general de la empresa y estrategia competitiva. Es la familia con más recorrido en las dos mallas: Gerencia Estratégica, Gestión Organizacional, Pensamiento Sistémico y las asignaturas integradoras. El escalonamiento por niveles (T-Shirt → Business21 → Businessglobal → Business Strategy) permite proponer un uso progresivo desde primer semestre hasta el ciclo profesional.
A22: Marketing y ventas | B22: Aplica de forma clara en una sola asignatura de las dos mallas: MERCADEO (Ing. Industrial, VI). Aporte parcial en Fundamento(s) de Economía y en Diseño de Productos y Servicios. Ing. de Sistemas no tiene asignaturas de mercadeo.
A23: Finanzas y banca | B23: Aplica en la línea financiera de Ing. Industrial: Contabilidad y Presupuesto (ContaTrainer, nivel 1-2), Finanzas e Ingeniería Económica (Kapital), Costos de Operación. Los simuladores de banca (Bankgame, BANKCOMPANY) no tienen asignatura destino en estas dos mallas.
A24: Emprendimiento | B24: Hallazgo relevante: ninguna de las dos mallas tiene una asignatura de emprendimiento o creación de empresa. La familia aplica de forma indirecta en Formulación y Evaluación de Proyectos (ambos programas) y es la candidata natural para ocupar un espacio electivo u optativo.
A25: Business Transformation | B25: Segunda familia con mayor potencial. Encaja en Gestión de Tecnología (Ind., VI), Arquitectura Empresarial (Sist., VIII), Inteligencia Artificial, Arquitectura de Información, Pensamiento Sistémico y Diseño de Productos y Servicios. Es la familia que mejor conecta con la agenda de transformación digital de las facultades de ingeniería.
A26: HORECA | B26: No aplica a estas dos mallas. Ninguna asignatura de Ingeniería Industrial ni de Ingeniería de Sistemas trabaja el sector hotelero o de restauración. Se deja registrada en Baja de forma explícita: proponerla aquí restaría credibilidad. Su destino en esta universidad serían otros programas (Administración Turística y Hotelera, si existe).
A27: ESG Management | B27: Hallazgo relevante: CÁTEDRA DE SOSTENIBILIDAD existe en los dos programas (Ing. Industrial V, Ing. de Sistemas IV) y hoy no tiene ninguna herramienta práctica asociada. Es la oportunidad de mayor relación esfuerzo-resultado de todo el catálogo CompanyGame, porque es una asignatura obligatoria en ambos programas y el simulador cubre su objeto completo.
A29: Ruta de implementación por programa
A30: Programa | B30: Prioridad | C30: Asignatura o espacio curricular | D30: Semestre | E30: Simulador | F30: Acción sugerida | G30: Horizonte
A31: Ing. Industrial | B31: Prioridad 1 - Implementación inmediata | C31: GERENCIA ESTRATÉGICA | D31: 4 | E31: SimVenture | F31: Demostración al docente titular y piloto en un grupo durante un semestre. | G31: 0-6 meses
A32: Ing. Industrial | B32: Prioridad 1 - Implementación inmediata | C32: FINANZAS | D32: 6 | E32: SimVenture | F32: Extender el piloto de SimVenture a la línea financiera del programa. | G32: 0-6 meses
A33: Ing. Industrial | B33: Prioridad 1 - Implementación inmediata | C33: MERCADEO | D33: 6 | E33: SimVenture | F33: Incluir en el mismo acuerdo de licenciamiento de Gerencia Estratégica y Finanzas. | G33: 0-6 meses
A34: Ing. Industrial | B34: Prioridad 1 - Implementación inmediata | C34: FORMULACIÓN Y EVALUACIÓN DE PROYECTOS | D34: 7 | E34: SimVenture + SimProject | F34: Propuesta de paquete doble; es el mejor caso para introducir SimProject en el programa. | G34: 0-6 meses
A35: Ing. Industrial | B35: Prioridad 1 - Implementación inmediata | C35: INGENIERÍA APLICADA | D35: 8 | E35: SimProject | F35: Presentar como herramienta de evaluación homogénea de proyectos. | G35: 0-6 meses
A36: Ing. Industrial | B36: Prioridad 2 - Potencial de implementación | C36: DISEÑO DE PRODUCTOS Y SERVICIOS | D36: 5 | E36: SimAgile + SimVenture | F36: Taller demostrativo con el docente; es la puerta de entrada de SimAgile al programa. | G36: 6-12 meses
A37: Ing. Industrial | B37: Prioridad 2 - Potencial de implementación | C37: GESTIÓN DE TECNOLOGÍA | D37: 6 | E37: SimAgile | F37: Vincular a la conversación de innovación y transformación digital de la facultad. | G37: 6-12 meses
A38: Ing. Industrial | B38: Prioridad 2 - Potencial de implementación | C38: INGENIERÍA ECONÓMICA | D38: 5 | E38: SimVenture + SimProject | F38: Demostración centrada en los reportes financieros del simulador. | G38: 6-12 meses
A39: Ing. Industrial | B39: Prioridad 2 - Potencial de implementación | C39: GESTIÓN ORGANIZACIONAL | D39: 3 | E39: SimVenture | F39: Incluir dentro del acuerdo de programa, no como venta aislada (2 créditos). | G39: 6-12 meses
A40: Ing. Industrial | B40: Prioridad 2 - Potencial de implementación | C40: COSTOS DE OPERACIÓN / CONTABILIDAD Y PRESUPUESTO | D40: 4 | E40: SimVenture | F40: Ampliación del acuerdo hacia la línea de costos y contabilidad. | G40: 6-12 meses
A41: Ing. Industrial | B41: Prioridad 2 - Potencial de implementación | C41: INVESTIGACIÓN OPERATIVA II | D41: 6 | E41: SimProject | F41: Uso complementario limitado a la unidad de PERT/CPM. | G41: 6-12 meses
A42: Ing. Industrial | B42: Prioridad 2 - Potencial de implementación | C42: ELECTIVAS I-III y OPTATIVAS I-III | D42: Varios | E42: Según contenido | F42: Proponer el diseño de una electiva u optativa basada en simulador; no requiere rediseño curricular. | G42: 6-12 meses
A43: Ing. Industrial | B43: Prioridad 3 - Oportunidades de desarrollo propio | C43: PLANEACIÓN Y CONTROL DE LA PRODUCCIÓN Y OPERACIONES + línea de operaciones | D43: 6 | E43: DP-01 Operaciones | F43: Levantar requerimientos con los docentes de la línea de producción; es el mayor vacío del portafolio. | G43: 12-24 meses
A44: Ing. Industrial | B44: Prioridad 3 - Oportunidades de desarrollo propio | C44: LOGÍSTICA Y CADENA DE SUMINISTRO | D44: 8 | E44: DP-04 Cadena de suministro | F44: Explorar como segundo desarrollo, reutilizando el motor de DP-01. | G44: 12-24 meses
A45: Ing. Industrial | B45: Prioridad 3 - Oportunidades de desarrollo propio | C45: SISTEMA INTEGRADO DE GESTIÓN / CONTROL ESTADÍSTICA DE LA CALIDAD | D45: 5 | E45: DP-03 SGI y DP-06 Calidad | F45: Desarrollo compartido con Ing. de Sistemas para duplicar el retorno. | G45: 12-24 meses
A46: Ing. de Sistemas | B46: Prioridad 1 - Implementación inmediata | C46: GESTIÓN DE PROYECTOS DE INGENIERÍA | D46: 7 | E46: SimProject | F46: Es el encaje más directo de todo el análisis; iniciar aquí la conversación con el programa. | G46: 0-6 meses
A47: Ing. de Sistemas | B47: Prioridad 1 - Implementación inmediata | C47: INGENIERÍA DEL SOFTWARE III | D47: 5 | E47: SimAgile + SimProject | F47: Propuesta de paquete doble con el mismo docente de gestión de proyectos. | G47: 0-6 meses
A48: Ing. de Sistemas | B48: Prioridad 1 - Implementación inmediata | C48: INGENIERÍA DE SOFTWARE II | D48: 4 | E48: SimAgile | F48: Extender SimAgile hacia abajo en la línea de ingeniería de software. | G48: 0-6 meses
A49: Ing. de Sistemas | B49: Prioridad 1 - Implementación inmediata | C49: FORMULACIÓN Y EVALUACIÓN DE PROYECTOS | D49: 6 | E49: SimProject + SimVenture | F49: Reutilizar el argumento ya validado en Ing. Industrial. | G49: 0-6 meses
A50: Ing. de Sistemas | B50: Prioridad 1 - Implementación inmediata | C50: GERENCIA ESTRATÉGICA | D50: 8 | E50: SimVenture o Businessglobal / Business Strategy | F50: Introducir la línea de estrategia en el programa; ofrecer dos niveles de precio. | G50: 0-6 meses
A51: Ambos programas | B51: Prioridad 1 - Implementación inmediata | C51: CÁTEDRA DE SOSTENIBILIDAD | D51: V / IV | E51: ESGManagement o ESGProject (CompanyGame) | F51: Presentar como propuesta de facultad: asignatura obligatoria en los dos programas y hoy sin ninguna herramienta asociada. | G51: 0-6 meses
A52: Ambos programas | B52: Prioridad 2 - Potencial de implementación | C52: INTRODUCCIÓN A LA INGENIERÍA | D52: I | E52: T-Shirt o Sunny Day (CompanyGame) | F52: Entrada temprana de bajo costo y alto volumen; prepara el terreno para simuladores de nivel superior. | G52: 6-12 meses
A53: Ing. de Sistemas | B53: Prioridad 2 - Potencial de implementación | C53: INGENIERÍA DE SOFTWARE I | D53: 3 | E53: SimAgile | F53: Entrada temprana con alto volumen de estudiantes. | G53: 6-12 meses
A54: Ing. de Sistemas | B54: Prioridad 2 - Potencial de implementación | C54: ARQUITECTURA EMPRESARIAL | D54: 8 | E54: SimAgile + SimVenture | F54: Requiere demostración; es la oportunidad más diferenciadora del programa. | G54: 6-12 meses
A55: Ing. de Sistemas | B55: Prioridad 2 - Potencial de implementación | C55: INGENIERÍA APLICADA | D55: 8 | E55: SimProject + SimAgile | F55: Cerrar junto con Ing. Industrial en la conversación de facultad. | G55: 6-12 meses
A56: Ing. de Sistemas | B56: Prioridad 2 - Potencial de implementación | C56: PENSAMIENTO SISTÉMICO | D56: 2 | E56: SimVenture | F56: Argumento conceptual fuerte; incluir dentro del acuerdo de programa (2 créditos). | G56: 6-12 meses
A57: Ing. de Sistemas | B57: Prioridad 2 - Potencial de implementación | C57: FUNDAMENTOS DE ECONOMÍA / PRÁCTICA EMPRESARIAL | D57: 5 y 8 | E57: SimVenture | F57: Uso complementario y de preparación previa a la práctica. | G57: 6-12 meses
A58: Ing. de Sistemas | B58: Prioridad 2 - Potencial de implementación | C58: ELECTIVAS I-III y OPTATIVAS I-III | D58: Varios | E58: Según contenido | F58: Proponer una electiva u optativa basada en simulador; vía más rápida de inserción. | G58: 6-12 meses
A59: Ing. de Sistemas | B59: Prioridad 2 - Potencial de implementación | C59: ARQUITECTURA EMPRESARIAL + INTELIGENCIA ARTIFICIAL | D59: 8 | E59: TRANSFORMA / Global2030 (CompanyGame) | F59: Ofrecer primero la familia Business Transformation del catálogo; el desarrollo propio DP-02 sólo si el programa exige mayor especificidad. | G59: 6-12 meses
A60: Ing. de Sistemas | B60: Prioridad 3 - Oportunidades de desarrollo propio | C60: SEGURIDAD DE LA INFORMACIÓN | D60: 7 | E60: DP-05 Gestión de incidentes | F60: Tema de alta demanda sin oferta local relevante en español. | G60: 12-24 meses
A61: Ing. de Sistemas | B61: Prioridad 3 - Oportunidades de desarrollo propio | C61: SISTEMAS INTEGRADOS DE GESTIÓN | D61: 8 | E61: DP-03 SGI | F61: Desarrollo compartido con Ing. Industrial. | G61: 12-24 meses
A63: Recomendaciones para la conversación comercial
A64: • Entrar por Ingeniería de Sistemas con SimProject en GESTIÓN DE PROYECTOS DE INGENIERÍA (VII): es el encaje más directo del análisis y la conversación que menos argumentación requiere. Una vez validado, el mismo docente suele tener a cargo INGENIERÍA DEL SOFTWARE III.
A65: • Entrar por Ingeniería Industrial con SimVenture o Businessglobal en GERENCIA ESTRATÉGICA (IV) y extender a FINANZAS y MERCADEO (VI) dentro del mismo acuerdo. Vender la línea completa, no la asignatura suelta.
A66: • Llevar la CÁTEDRA DE SOSTENIBILIDAD con ESGManagement como propuesta de facultad y no de programa: es obligatoria en Ingeniería Industrial e Ingeniería de Sistemas, hoy no usa ninguna herramienta y una sola conversación cubre los dos programas.
A67: • Usar el escalonamiento por niveles del catálogo CompanyGame como argumento de continuidad: T-Shirt o Sunny Day en primer semestre, Business21 en el ciclo intermedio y Businessglobal o Business Strategy en el ciclo profesional. Convierte una venta puntual en una ruta de varios años.
A68: • Usar FORMULACIÓN Y EVALUACIÓN DE PROYECTOS como caso de paquete doble: existe en los dos programas y admite SimVenture y SimProject con justificación académica distinta para cada uno, además de la familia Emprendimiento de CompanyGame.
A69: • Proponer un piloto de un semestre en un solo grupo antes de negociar licenciamiento por programa. Reduce la resistencia del director y genera el testimonio docente que sostiene la venta siguiente.
A70: • Aprovechar los 12 espacios electivos y optativos: diseñar una electiva basada en simulador es la vía de inserción más rápida porque no exige modificar el plan de estudios ni pasar por comité curricular. Es también la única entrada directa de la familia Emprendimiento.
A71: • No ofrecer la familia HORECA a esta facultad y no forzar la oferta en ciencias básicas ni en las asignaturas técnicas de programación, redes y bases de datos. La credibilidad de la propuesta ante el decano depende de haber marcado esas asignaturas como no aplicables.
A72: • Levantar los microcurrículos de las 15 asignaturas priorizadas antes de la reunión: las competencias de este análisis son inferencias basadas en el nombre y la ubicación de la asignatura, y el syllabus permitirá afinar el argumento con el lenguaje del propio programa.
A73: • Presentar los desarrollos propios DP-01 (operaciones), DP-02 (transformación digital) y DP-03 (sistemas de gestión) como coinversión o proyecto conjunto con la facultad, no como producto terminado: son oportunidades de mediano plazo que además diferencian frente a la competencia.

Sheet Catálogo CompanyGame
A1: Catálogo CompanyGame y su aplicación a las dos mallas
A2: 41 simuladores en 7 familias, según el cuadro de portafolio entregado por el cliente
A4: Familia | B4: Simulador | C4: Nivel | D4: Aplicación en estas dos mallas
A5: Negocios y estrategia | B5: T-Shirt | C5: Niveles 1 a 2 | D5: Gestión general de la empresa y estrategia competitiva. Es la familia con más recorrido en las dos mallas: Gerencia Estratégica, Gestión Organizacional, Pensamiento Sistémico y las asignaturas integradoras. El escalonamiento por niveles (T-Shirt → Business21 → Businessglobal → Business Strategy) permite proponer un uso progresivo desde primer semestre hasta el ciclo profesional.
B6: Sunny Day | C6: Niveles 1 a 2
B7: Energy&Co | C7: Niveles 1 a 2
B8: Business21 | C8: Niveles 3 y 4
B9: Businessglobal | C9: Nivel 5
B10: Business Strategy | C10: Niveles 6 y 7
A11: Marketing y ventas | B11: MarketGame | C11: Niveles 1 a 2 | D11: Aplica de forma clara en una sola asignatura de las dos mallas: MERCADEO (Ing. Industrial, VI). Aporte parcial en Fundamento(s) de Economía y en Diseño de Productos y Servicios. Ing. de Sistemas no tiene asignaturas de mercadeo.
B12: Coffee Time | C12: Niveles 1 a 2
B13: SalesManager | C13: Niveles 3 y 4
B14: Food Company | C14: Niveles 3 y 4
B15: TechCompany | C15: Nivel 5
B16: GlobalMARKET | C16: Niveles 6 y 7
B17: FOCUS | C17: Niveles 6 y 7
A18: Finanzas y banca | B18: ContaTrainer | C18: Niveles 1 a 2 | D18: Aplica en la línea financiera de Ing. Industrial: Contabilidad y Presupuesto (ContaTrainer, nivel 1-2), Finanzas e Ingeniería Económica (Kapital), Costos de Operación. Los simuladores de banca (Bankgame, BANKCOMPANY) no tienen asignatura destino en estas dos mallas.
B19: Advisor Jr. | C19: Niveles 3 y 4
B20: CORBATUL | C20: Niveles 3 y 4
B21: Bankgame | C21: Nivel 5
B22: Kapital | C22: Nivel 5
B23: BANKCOMPANY | C23: Niveles 6 y 7
A24: Emprendimiento | B24: FitnessGym | C24: Niveles 3 y 4 | D24: Hallazgo relevante: ninguna de las dos mallas tiene una asignatura de emprendimiento o creación de empresa. La familia aplica de forma indirecta en Formulación y Evaluación de Proyectos (ambos programas) y es la candidata natural para ocupar un espacio electivo u optativo.
B25: Luxe Atelier | C25: Niveles 3 y 4
B26: Business Chef | C26: Nivel 5
B27: FitnessGym Executive | C27: Niveles 6 y 7
A28: Business Transformation | B28: InnovaTech | C28: Niveles 3 y 4 | D28: Segunda familia con mayor potencial. Encaja en Gestión de Tecnología (Ind., VI), Arquitectura Empresarial (Sist., VIII), Inteligencia Artificial, Arquitectura de Información, Pensamiento Sistémico y Diseño de Productos y Servicios. Es la familia que mejor conecta con la agenda de transformación digital de las facultades de ingeniería.
B29: InterPyme | C29: Niveles 3 y 4
B30: Avocado Expand | C30: Niveles 3 y 4
B31: Acelera | C31: Niveles 3 y 4 / Nivel 5
B32: Organization & People Management | C32: Niveles 3 y 4 / Nivel 5
B33: Global2020 | C33: Nivel 5
B34: TRANSFORMA | C34: Niveles 6 y 7
B35: Global2030 | C35: Niveles 6 y 7
A36: HORECA | B36: Hotel Virtual | C36: Niveles 1 a 2 | D36: No aplica a estas dos mallas. Ninguna asignatura de Ingeniería Industrial ni de Ingeniería de Sistemas trabaja el sector hotelero o de restauración. Se deja registrada en Baja de forma explícita: proponerla aquí restaría credibilidad. Su destino en esta universidad serían otros programas (Administración Turística y Hotelera, si existe).
B37: hotel game | C37: Niveles 1 a 2
B38: Casa Guadalupe | C38: Niveles 3 y 4
B39: Five Stars | C39: Niveles 3 y 4
B40: InnovaHotel | C40: Nivel 5
B41: Hotel Manager | C41: Niveles 6 y 7
B42: HotelCompany | C42: Niveles 6 y 7
A43: ESG Management | B43: ESGProject | C43: Niveles 3 y 4 | D43: Hallazgo relevante: CÁTEDRA DE SOSTENIBILIDAD existe en los dos programas (Ing. Industrial V, Ing. de Sistemas IV) y hoy no tiene ninguna herramienta práctica asociada. Es la oportunidad de mayor relación esfuerzo-resultado de todo el catálogo CompanyGame, porque es una asignatura obligatoria en ambos programas y el simulador cubre su objeto completo.
B44: ESGManagement | C44: Nivel 5
B45: GlobalManagement | C45: Niveles 6 y 7
A47: Los niveles corresponden a las columnas del cuadro de portafolio (Niveles 1 a 2 / Niveles 3 y 4 / Nivel 5 / Niveles 6 y 7). En dos casos la ubicación del simulador en el cuadro queda entre dos columnas y se registra como tal. SimVenture, SimAgile y SimProject se analizan en columnas propias de las matrices por tratarse de productos distintos a este catálogo.
